{
 "source_file": "../data/maps/plan12",
 "position": {
  "x":29953,
  "y":33090,
  "h":159
  },
 "gfx": [
  {
   "name":"explo",
   "width":96,
   "height":128,
   "frames":2,
   "type":88,
   "anim":2,
   "t":3
  },
  {
   "name":"widok-planeta",
   "width":256,
   "height":128,
   "frames":0,
   "type":0,
   "anim":0,
   "t":0
  },
  {
   "name":"wzorek2c",
   "width":64,
   "height":64,
   "frames":0,
   "type":1,
   "anim":0,
   "t":0
  },
  {
   "name":"skrzyp",
   "width":706,
   "height":3178,
   "frames":0,
   "type":256,
   "anim":0,
   "t":0
  },
  {
   "name":"bigbang",
   "width":80,
   "height":160,
   "frames":0,
   "type":64,
   "anim":0,
   "t":0
  },
  {
   "name":"grob",
   "width":32,
   "height":49,
   "frames":3,
   "type":4,
   "anim":0,
   "t":0
  },
  {
   "name":"sciana-ufo-tele1",
   "width":128,
   "height":64,
   "frames":1,
   "type":1,
   "anim":0,
   "t":0
  },
  {
   "name":"wzorek2",
   "width":64,
   "height":64,
   "frames":0,
   "type":1,
   "anim":0,
   "t":0
  },
  {
   "name":"wzorek3c-j",
   "width":64,
   "height":64,
   "frames":0,
   "type":0,
   "anim":0,
   "t":0
  },
  {
   "name":"osmior-zol",
   "width":80,
   "height":110,
   "frames":1,
   "type":0,
   "anim":0,
   "t":0
  },
  {
   "name":"osmior-zol-pif",
   "width":24,
   "height":96,
   "frames":1,
   "type":0,
   "anim":1,
   "t":0
  },
  {
   "name":"osmior-zol-boli",
   "width":80,
   "height":110,
   "frames":0,
   "type":0,
   "anim":0,
   "t":0
  },
  {
   "name":"osmior-zol-trup",
   "width":80,
   "height":110,
   "frames":1,
   "type":8,
   "anim":1,
   "t":7
  },
  {
   "name":"wzorek2x",
   "width":64,
   "height":64,
   "frames":0,
   "type":0,
   "anim":0,
   "t":0
  },
  {
   "name":"wzorek2-okno",
   "width":64,
   "height":64,
   "frames":0,
   "type":3,
   "anim":0,
   "t":0
  },
  {
   "name":"wzorek2x-j",
   "width":64,
   "height":64,
   "frames":0,
   "type":0,
   "anim":0,
   "t":0
  },
  {
   "name":"wzorek2c-kraty",
   "width":64,
   "height":64,
   "frames":0,
   "type":1,
   "anim":0,
   "t":0
  },
  {
   "name":"wzorek4c",
   "width":64,
   "height":64,
   "frames":0,
   "type":1,
   "anim":0,
   "t":0
  },
  {
   "name":"wzorek4",
   "width":64,
   "height":64,
   "frames":0,
   "type":1,
   "anim":0,
   "t":0
  },
  {
   "name":"karabin",
   "width":16,
   "height":7,
   "frames":0,
   "type":0,
   "anim":0,
   "t":0
  },
  {
   "name":"wzorek2-drzwi",
   "width":64,
   "height":64,
   "frames":0,
   "type":1,
   "anim":0,
   "t":0
  },
  {
   "name":"ufo-kula",
   "width":32,
   "height":90,
   "frames":0,
   "type":0,
   "anim":0,
   "t":0
  },
  {
   "name":"alien-lampa",
   "width":48,
   "height":48,
   "frames":2,
   "type":0,
   "anim":2,
   "t":1
  },
  {
   "name":"stalagmit",
   "width":48,
   "height":71,
   "frames":2,
   "type":0,
   "anim":2,
   "t":3
  },
  {
   "name":"granat",
   "width":16,
   "height":25,
   "frames":0,
   "type":0,
   "anim":0,
   "t":0
  },
  {
   "name":"wzorek3c",
   "width":64,
   "height":64,
   "frames":0,
   "type":0,
   "anim":0,
   "t":0
  },
  {
   "name":"laser",
   "width":64,
   "height":64,
   "frames":0,
   "type":0,
   "anim":0,
   "t":0
  },
  {
   "name":"wzorek2xx",
   "width":64,
   "height":64,
   "frames":0,
   "type":0,
   "anim":0,
   "t":0
  },
  {
   "name":"wzorek3cx",
   "width":64,
   "height":64,
   "frames":0,
   "type":0,
   "anim":0,
   "t":0
  },
  {
   "name":"wzorek5",
   "width":64,
   "height":64,
   "frames":0,
   "type":1,
   "anim":0,
   "t":0
  },
  {
   "name":"wzorek5c",
   "width":64,
   "height":64,
   "frames":0,
   "type":1,
   "anim":0,
   "t":0
  },
  {
   "name":"wzorek5-drzwi",
   "width":64,
   "height":64,
   "frames":0,
   "type":1,
   "anim":0,
   "t":0
  },
  {
   "name":"widelec",
   "width":16,
   "height":256,
   "frames":0,
   "type":0,
   "anim":0,
   "t":0
  },
  {
   "name":"klucz",
   "width":0,
   "height":0,
   "frames":0,
   "type":0,
   "anim":0,
   "t":3
  },
  {
   "name":"alien-zasadzka",
   "width":32,
   "height":24,
   "frames":3,
   "type":0,
   "anim":0,
   "t":3
  },
  {
   "name":"alien-zasadzka-r",
   "width":32,
   "height":24,
   "frames":3,
   "type":0,
   "anim":3,
   "t":0
  },
  {
   "name":"rakieta",
   "width":32,
   "height":18,
   "frames":0,
   "type":0,
   "anim":0,
   "t":0
  },
  {
   "name":"rakieta2",
   "width":128,
   "height":18,
   "frames":3,
   "type":4,
   "anim":0,
   "t":0
  },
  {
   "name":"kolumna-skal",
   "width":16,
   "height":128,
   "frames":0,
   "type":0,
   "anim":0,
   "t":0
  },
  {
   "name":"tlo",
   "width":0,
   "height":0,
   "frames":0,
   "type":256,
   "anim":0,
   "t":0
  },
  {
   "name":"radar",
   "width":0,
   "height":0,
   "frames":0,
   "type":0,
   "anim":0,
   "t":0
  },
  {
   "name":"alien-drzwi",
   "width":0,
   "height":0,
   "frames":0,
   "type":1,
   "anim":0,
   "t":0
  }
  ],
 "pts": [
  { "x":35101, "y":33495 },
  { "x":34933, "y":33096 },
  { "x":34957, "y":33334 },
  { "x":35342, "y":33516 },
  { "x":35337, "y":33264 },
  { "x":35159, "y":33243 },
  { "x":31798, "y":33208 },
  { "x":31592, "y":33208 },
  { "x":32012, "y":33208 },
  { "x":31413, "y":33208 },
  { "x":32012, "y":33008 },
  { "x":31413, "y":33008 },
  { "x":32211, "y":33008 },
  { "x":31221, "y":33008 },
  { "x":32019, "y":32798 },
  { "x":32218, "y":32798 },
  { "x":31413, "y":32788 },
  { "x":31167, "y":32798 },
  { "x":32019, "y":32608 },
  { "x":31413, "y":32608 },
  { "x":31606, "y":32608 },
  { "x":31819, "y":32598 },
  { "x":31813, "y":32408 },
  { "x":31606, "y":32418 },
  { "x":32388, "y":32798 },
  { "x":32392, "y":33008 },
  { "x":31813, "y":32228 },
  { "x":31600, "y":32238 },
  { "x":31813, "y":32028 },
  { "x":31613, "y":32028 },
  { "x":31400, "y":32238 },
  { "x":31421, "y":32028 },
  { "x":31181, "y":32028 },
  { "x":30954, "y":32028 },
  { "x":31188, "y":32238 },
  { "x":30947, "y":32238 },
  { "x":30720, "y":32028 },
  { "x":30727, "y":32238 },
  { "x":30715, "y":31848 },
  { "x":30727, "y":32418 },
  { "x":30727, "y":32588 },
  { "x":30727, "y":32788 },
  { "x":30940, "y":32788 },
  { "x":31215, "y":33198 },
  { "x":31215, "y":33398 },
  { "x":31215, "y":33578 },
  { "x":30988, "y":33578 },
  { "x":30768, "y":33568 },
  { "x":30548, "y":33568 },
  { "x":30548, "y":33378 },
  { "x":30548, "y":33168 },
  { "x":30542, "y":32988 },
  { "x":30542, "y":32798 },
  { "x":30363, "y":32898 },
  { "x":30280, "y":33108 },
  { "x":30253, "y":33288 },
  { "x":30542, "y":32578 },
  { "x":30548, "y":32378 },
  { "x":30383, "y":32448 },
  { "x":30301, "y":32258 },
  { "x":30253, "y":33508 },
  { "x":30273, "y":32038 },
  { "x":30273, "y":31828 },
  { "x":30543, "y":32138 },
  { "x":30543, "y":31918 },
  { "x":30530, "y":31708 },
  { "x":30328, "y":32668 },
  { "x":30191, "y":32798 },
  { "x":30191, "y":32518 },
  { "x":29978, "y":32798 },
  { "x":29971, "y":32518 },
  { "x":29868, "y":32668 },
  { "x":29668, "y":32548 },
  { "x":29799, "y":32408 },
  { "x":29668, "y":32778 },
  { "x":29792, "y":32908 },
  { "x":29668, "y":32318 },
  { "x":29670, "y":33008 },
  { "x":29847, "y":33108 },
  { "x":29847, "y":32228 },
  { "x":29670, "y":32108 },
  { "x":29668, "y":33238 },
  { "x":29861, "y":32028 },
  { "x":29904, "y":33268 },
  { "x":30129, "y":33018 },
  { "x":30026, "y":33008 },
  { "x":30067, "y":33198 },
  { "x":30067, "y":33418 },
  { "x":29657, "y":33448 },
  { "x":30067, "y":33628 },
  { "x":30067, "y":33838 },
  { "x":30253, "y":33738 },
  { "x":30370, "y":33898 },
  { "x":30542, "y":33998 },
  { "x":30177, "y":33978 },
  { "x":30287, "y":34118 },
  { "x":30459, "y":34198 },
  { "x":30686, "y":34238 },
  { "x":30899, "y":34248 },
  { "x":31126, "y":34258 },
  { "x":31332, "y":34258 },
  { "x":30748, "y":34038 },
  { "x":30961, "y":34048 },
  { "x":31181, "y":34058 },
  { "x":31394, "y":34058 },
  { "x":31573, "y":34248 },
  { "x":31621, "y":34038 },
  { "x":31813, "y":34218 },
  { "x":32019, "y":34118 },
  { "x":32156, "y":33958 },
  { "x":32225, "y":33758 },
  { "x":31813, "y":33948 },
  { "x":31957, "y":33788 },
  { "x":31964, "y":33568 },
  { "x":32429, "y":33758 },
  { "x":31964, "y":33378 },
  { "x":32170, "y":33378 },
  { "x":32390, "y":33378 },
  { "x":30983, "y":33818 },
  { "x":30768, "y":33798 },
  { "x":32388, "y":33198 },
  { "x":32566, "y":33588 },
  { "x":32566, "y":33368 },
  { "x":32566, "y":33178 },
  { "x":32566, "y":33018 },
  { "x":32559, "y":32788 },
  { "x":32564, "y":32578 },
  { "x":32392, "y":32558 },
  { "x":29856, "y":31838 },
  { "x":30069, "y":31838 },
  { "x":29684, "y":31898 },
  { "x":29691, "y":31708 },
  { "x":29450, "y":32768 },
  { "x":29450, "y":32548 },
  { "x":29471, "y":32318 },
  { "x":29464, "y":32078 },
  { "x":29485, "y":31878 },
  { "x":29485, "y":31678 },
  { "x":29498, "y":31498 },
  { "x":29890, "y":31698 },
  { "x":30103, "y":31698 },
  { "x":30337, "y":31708 },
  { "x":29691, "y":31498 },
  { "x":29883, "y":31508 },
  { "x":30117, "y":31508 },
  { "x":30330, "y":31498 },
  { "x":30516, "y":31508 },
  { "x":30722, "y":31508 },
  { "x":30715, "y":31678 },
  { "x":29450, "y":32998 },
  { "x":29443, "y":33238 },
  { "x":29443, "y":33448 },
  { "x":29849, "y":33448 },
  { "x":29230, "y":33448 },
  { "x":29849, "y":33658 },
  { "x":29230, "y":33658 },
  { "x":29842, "y":33868 },
  { "x":29230, "y":33858 },
  { "x":29416, "y":33868 },
  { "x":29636, "y":33858 },
  { "x":32564, "y":32338 },
  { "x":32392, "y":32328 },
  { "x":32193, "y":32328 },
  { "x":32743, "y":32338 },
  { "x":32935, "y":32348 },
  { "x":31986, "y":32328 },
  { "x":32935, "y":32138 },
  { "x":32935, "y":31928 },
  { "x":31986, "y":32118 },
  { "x":31986, "y":31918 },
  { "x":32935, "y":31748 },
  { "x":31979, "y":31718 },
  { "x":32179, "y":31718 },
  { "x":32385, "y":31718 },
  { "x":32564, "y":31718 },
  { "x":32736, "y":31728 },
  { "x":33114, "y":31928 },
  { "x":33128, "y":32138 },
  { "x":33299, "y":32128 },
  { "x":33293, "y":31928 },
  { "x":33299, "y":31748 },
  { "x":33286, "y":32328 },
  { "x":33297, "y":31528 },
  { "x":33829, "y":31532 },
  { "x":33483, "y":32338 },
  { "x":33675, "y":32338 },
  { "x":33826, "y":32348 },
  { "x":33831, "y":32133 },
  { "x":33831, "y":31946 },
  { "x":33831, "y":31742 },
  { "x":33448, "y":31528 },
  { "x":33641, "y":31528 },
  { "x":33487, "y":32538 },
  { "x":33679, "y":32538 },
  { "x":33789, "y":32648 },
  { "x":33356, "y":32628 },
  { "x":33356, "y":32848 },
  { "x":33783, "y":32848 },
  { "x":33453, "y":32958 },
  { "x":33686, "y":32958 },
  { "x":34053, "y":31742 },
  { "x":34053, "y":31946 },
  { "x":34278, "y":31744 },
  { "x":34284, "y":31946 },
  { "x":34476, "y":31750 },
  { "x":34669, "y":31750 },
  { "x":34486, "y":31946 },
  { "x":34678, "y":31946 },
  { "x":34674, "y":31540 },
  { "x":34672, "y":32160 },
  { "x":34864, "y":31962 },
  { "x":34870, "y":32160 },
  { "x":34870, "y":31746 },
  { "x":34864, "y":31566 },
  { "x":35056, "y":31755 },
  { "x":35056, "y":31575 },
  { "x":35050, "y":31971 },
  { "x":35050, "y":32151 },
  { "x":34666, "y":32349 },
  { "x":34679, "y":31368 },
  { "x":34890, "y":32366 },
  { "x":34883, "y":31368 },
  { "x":35062, "y":31377 },
  { "x":35076, "y":32375 },
  { "x":35254, "y":32375 },
  { "x":35266, "y":31386 },
  { "x":35173, "y":31872 },
  { "x":35290, "y":31737 },
  { "x":35284, "y":32016 },
  { "x":35483, "y":31214 },
  { "x":35197, "y":31611 },
  { "x":35173, "y":32133 },
  { "x":35347, "y":31619 },
  { "x":35322, "y":32141 },
  { "x":35267, "y":31214 },
  { "x":35236, "y":32564 },
  { "x":35458, "y":32573 },
  { "x":35396, "y":31394 },
  { "x":35551, "y":31394 },
  { "x":35372, "y":32375 },
  { "x":35520, "y":32375 },
  { "x":35663, "y":31223 },
  { "x":35867, "y":31223 },
  { "x":35632, "y":32582 },
  { "x":35830, "y":32591 },
  { "x":35830, "y":32366 },
  { "x":35495, "y":32213 },
  { "x":35520, "y":31547 },
  { "x":35427, "y":31754 },
  { "x":35421, "y":32015 },
  { "x":35867, "y":31430 },
  { "x":35601, "y":31754 },
  { "x":35613, "y":32015 },
  { "x":35737, "y":31547 },
  { "x":35693, "y":32213 },
  { "x":35762, "y":31664 },
  { "x":35762, "y":32150 },
  { "x":35762, "y":31835 },
  { "x":35768, "y":31970 },
  { "x":35929, "y":32258 },
  { "x":35947, "y":31529 },
  { "x":35935, "y":32006 },
  { "x":35941, "y":31772 },
  { "x":35635, "y":32840 },
  { "x":35435, "y":32828 },
  { "x":33655, "y":31724 },
  { "x":33466, "y":31724 },
  { "x":35635, "y":33068 },
  { "x":35452, "y":33056 },
  { "x":35254, "y":33056 },
  { "x":35237, "y":32828 },
  { "x":35154, "y":33131 },
  { "x":35039, "y":32893 }
  ],
 "seg": [
  {
   "p1":2,
   "p2":3,
   "gfx":18,
   "flags":1,
   "dx":1,
   "dy":0
  },
  {
   "p1":1,
   "p2":4,
   "gfx":18,
   "flags":1,
   "dx":0,
   "dy":0
  },
  {
   "p1":6,
   "p2":5,
   "gfx":18,
   "flags":1,
   "dx":0,
   "dy":0
  },
  {
   "p1":4,
   "p2":5,
   "gfx":18,
   "flags":1,
   "dx":0,
   "dy":0
  },
  {
   "p1":3,
   "p2":1,
   "gfx":18,
   "flags":1,
   "dx":0,
   "dy":0
  },
  {
   "p1":8,
   "p2":7,
   "gfx":8,
   "flags":1,
   "dx":0,
   "dy":0
  },
  {
   "p1":273,
   "p2":2,
   "gfx":18,
   "flags":1,
   "dx":0,
   "dy":0
  },
  {
   "p1":7,
   "p2":9,
   "gfx":8,
   "flags":1,
   "dx":0,
   "dy":0
  },
  {
   "p1":8,
   "p2":10,
   "gfx":8,
   "flags":1,
   "dx":0,
   "dy":0
  },
  {
   "p1":9,
   "p2":11,
   "gfx":3,
   "flags":1,
   "dx":0,
   "dy":0
  },
  {
   "p1":10,
   "p2":12,
   "gfx":3,
   "flags":1,
   "dx":0,
   "dy":0
  },
  {
   "p1":11,
   "p2":13,
   "gfx":8,
   "flags":1,
   "dx":0,
   "dy":0
  },
  {
   "p1":12,
   "p2":14,
   "gfx":8,
   "flags":1,
   "dx":0,
   "dy":0
  },
  {
   "p1":15,
   "p2":16,
   "gfx":8,
   "flags":1,
   "dx":0,
   "dy":0
  },
  {
   "p1":17,
   "p2":18,
   "gfx":8,
   "flags":1,
   "dx":0,
   "dy":0
  },
  {
   "p1":15,
   "p2":19,
   "gfx":3,
   "flags":1,
   "dx":0,
   "dy":0
  },
  {
   "p1":17,
   "p2":20,
   "gfx":3,
   "flags":1,
   "dx":0,
   "dy":0
  },
  {
   "p1":20,
   "p2":21,
   "gfx":8,
   "flags":1,
   "dx":0,
   "dy":0
  },
  {
   "p1":19,
   "p2":22,
   "gfx":8,
   "flags":1,
   "dx":0,
   "dy":0
  },
  {
   "p1":22,
   "p2":23,
   "gfx":3,
   "flags":1,
   "dx":0,
   "dy":0
  },
  {
   "p1":21,
   "p2":24,
   "gfx":3,
   "flags":1,
   "dx":0,
   "dy":0
  },
  {
   "p1":16,
   "p2":25,
   "gfx":8,
   "flags":1,
   "dx":0,
   "dy":0
  },
  {
   "p1":13,
   "p2":26,
   "gfx":8,
   "flags":1,
   "dx":0,
   "dy":0
  },
  {
   "p1":23,
   "p2":27,
   "gfx":3,
   "flags":1,
   "dx":0,
   "dy":0
  },
  {
   "p1":24,
   "p2":28,
   "gfx":3,
   "flags":1,
   "dx":0,
   "dy":0
  },
  {
   "p1":27,
   "p2":29,
   "gfx":3,
   "flags":1,
   "dx":0,
   "dy":0
  },
  {
   "p1":29,
   "p2":30,
   "gfx":8,
   "flags":1,
   "dx":0,
   "dy":0
  },
  {
   "p1":28,
   "p2":31,
   "gfx":8,
   "flags":1,
   "dx":0,
   "dy":0
  },
  {
   "p1":30,
   "p2":32,
   "gfx":15,
   "flags":1,
   "dx":0,
   "dy":0
  },
  {
   "p1":32,
   "p2":33,
   "gfx":15,
   "flags":1,
   "dx":0,
   "dy":0
  },
  {
   "p1":33,
   "p2":34,
   "gfx":15,
   "flags":1,
   "dx":0,
   "dy":0
  },
  {
   "p1":31,
   "p2":35,
   "gfx":8,
   "flags":1,
   "dx":0,
   "dy":0
  },
  {
   "p1":35,
   "p2":36,
   "gfx":8,
   "flags":1,
   "dx":0,
   "dy":0
  },
  {
   "p1":34,
   "p2":37,
   "gfx":8,
   "flags":1,
   "dx":0,
   "dy":0
  },
  {
   "p1":36,
   "p2":38,
   "gfx":8,
   "flags":1,
   "dx":0,
   "dy":0
  },
  {
   "p1":37,
   "p2":39,
   "gfx":3,
   "flags":1,
   "dx":0,
   "dy":0
  },
  {
   "p1":38,
   "p2":40,
   "gfx":3,
   "flags":1,
   "dx":0,
   "dy":0
  },
  {
   "p1":40,
   "p2":41,
   "gfx":3,
   "flags":1,
   "dx":0,
   "dy":0
  },
  {
   "p1":41,
   "p2":42,
   "gfx":3,
   "flags":1,
   "dx":0,
   "dy":0
  },
  {
   "p1":42,
   "p2":43,
   "gfx":8,
   "flags":1,
   "dx":0,
   "dy":0
  },
  {
   "p1":43,
   "p2":18,
   "gfx":8,
   "flags":1,
   "dx":0,
   "dy":0
  },
  {
   "p1":14,
   "p2":44,
   "gfx":17,
   "flags":1,
   "dx":0,
   "dy":0
  },
  {
   "p1":44,
   "p2":45,
   "gfx":17,
   "flags":1,
   "dx":0,
   "dy":0
  },
  {
   "p1":45,
   "p2":46,
   "gfx":17,
   "flags":1,
   "dx":0,
   "dy":0
  },
  {
   "p1":46,
   "p2":47,
   "gfx":8,
   "flags":1,
   "dx":0,
   "dy":0
  },
  {
   "p1":47,
   "p2":48,
   "gfx":8,
   "flags":27,
   "dx":-12,
   "dy":12
  },
  {
   "p1":48,
   "p2":49,
   "gfx":8,
   "flags":1,
   "dx":0,
   "dy":0
  },
  {
   "p1":49,
   "p2":50,
   "gfx":17,
   "flags":1,
   "dx":0,
   "dy":0
  },
  {
   "p1":50,
   "p2":51,
   "gfx":17,
   "flags":1,
   "dx":0,
   "dy":0
  },
  {
   "p1":51,
   "p2":52,
   "gfx":17,
   "flags":1,
   "dx":0,
   "dy":0
  },
  {
   "p1":52,
   "p2":53,
   "gfx":3,
   "flags":1,
   "dx":0,
   "dy":0
  },
  {
   "p1":53,
   "p2":54,
   "gfx":8,
   "flags":1,
   "dx":0,
   "dy":0
  },
  {
   "p1":54,
   "p2":55,
   "gfx":8,
   "flags":1,
   "dx":0,
   "dy":0
  },
  {
   "p1":55,
   "p2":56,
   "gfx":3,
   "flags":1,
   "dx":0,
   "dy":0
  },
  {
   "p1":57,
   "p2":58,
   "gfx":3,
   "flags":1,
   "dx":0,
   "dy":0
  },
  {
   "p1":57,
   "p2":59,
   "gfx":8,
   "flags":1,
   "dx":0,
   "dy":0
  },
  {
   "p1":59,
   "p2":60,
   "gfx":8,
   "flags":1,
   "dx":0,
   "dy":0
  },
  {
   "p1":56,
   "p2":61,
   "gfx":3,
   "flags":1,
   "dx":0,
   "dy":0
  },
  {
   "p1":60,
   "p2":62,
   "gfx":3,
   "flags":1,
   "dx":0,
   "dy":0
  },
  {
   "p1":62,
   "p2":63,
   "gfx":3,
   "flags":1,
   "dx":0,
   "dy":0
  },
  {
   "p1":58,
   "p2":64,
   "gfx":3,
   "flags":1,
   "dx":0,
   "dy":0
  },
  {
   "p1":64,
   "p2":65,
   "gfx":3,
   "flags":1,
   "dx":0,
   "dy":0
  },
  {
   "p1":65,
   "p2":66,
   "gfx":3,
   "flags":1,
   "dx":0,
   "dy":0
  },
  {
   "p1":67,
   "p2":68,
   "gfx":3,
   "flags":1,
   "dx":0,
   "dy":0
  },
  {
   "p1":67,
   "p2":69,
   "gfx":3,
   "flags":1,
   "dx":0,
   "dy":0
  },
  {
   "p1":25,
   "p2":128,
   "gfx":3,
   "flags":1,
   "dx":0,
   "dy":0
  },
  {
   "p1":69,
   "p2":71,
   "gfx":8,
   "flags":1,
   "dx":0,
   "dy":0
  },
  {
   "p1":71,
   "p2":72,
   "gfx":3,
   "flags":1,
   "dx":0,
   "dy":0
  },
  {
   "p1":70,
   "p2":72,
   "gfx":3,
   "flags":1,
   "dx":0,
   "dy":0
  },
  {
   "p1":73,
   "p2":74,
   "gfx":8,
   "flags":1,
   "dx":0,
   "dy":0
  },
  {
   "p1":75,
   "p2":76,
   "gfx":8,
   "flags":1,
   "dx":0,
   "dy":0
  },
  {
   "p1":73,
   "p2":77,
   "gfx":18,
   "flags":1,
   "dx":0,
   "dy":0
  },
  {
   "p1":75,
   "p2":78,
   "gfx":18,
   "flags":1,
   "dx":0,
   "dy":0
  },
  {
   "p1":76,
   "p2":79,
   "gfx":8,
   "flags":1,
   "dx":0,
   "dy":0
  },
  {
   "p1":74,
   "p2":80,
   "gfx":8,
   "flags":1,
   "dx":0,
   "dy":0
  },
  {
   "p1":77,
   "p2":81,
   "gfx":18,
   "flags":1,
   "dx":0,
   "dy":0
  },
  {
   "p1":78,
   "p2":82,
   "gfx":18,
   "flags":1,
   "dx":0,
   "dy":0
  },
  {
   "p1":80,
   "p2":83,
   "gfx":3,
   "flags":1,
   "dx":0,
   "dy":0
  },
  {
   "p1":79,
   "p2":84,
   "gfx":3,
   "flags":1,
   "dx":0,
   "dy":0
  },
  {
   "p1":68,
   "p2":85,
   "gfx":17,
   "flags":1,
   "dx":0,
   "dy":0
  },
  {
   "p1":70,
   "p2":86,
   "gfx":17,
   "flags":1,
   "dx":0,
   "dy":0
  },
  {
   "p1":85,
   "p2":87,
   "gfx":17,
   "flags":1,
   "dx":0,
   "dy":0
  },
  {
   "p1":87,
   "p2":86,
   "gfx":17,
   "flags":1,
   "dx":0,
   "dy":0
  },
  {
   "p1":87,
   "p2":88,
   "gfx":17,
   "flags":1,
   "dx":0,
   "dy":0
  },
  {
   "p1":84,
   "p2":87,
   "gfx":7,
   "flags":1,
   "dx":0,
   "dy":0
  },
  {
   "p1":88,
   "p2":90,
   "gfx":3,
   "flags":1,
   "dx":0,
   "dy":0
  },
  {
   "p1":90,
   "p2":91,
   "gfx":3,
   "flags":1,
   "dx":0,
   "dy":0
  },
  {
   "p1":61,
   "p2":92,
   "gfx":3,
   "flags":1,
   "dx":0,
   "dy":0
  },
  {
   "p1":92,
   "p2":93,
   "gfx":8,
   "flags":1,
   "dx":0,
   "dy":0
  },
  {
   "p1":93,
   "p2":94,
   "gfx":8,
   "flags":1,
   "dx":0,
   "dy":0
  },
  {
   "p1":91,
   "p2":95,
   "gfx":8,
   "flags":1,
   "dx":0,
   "dy":0
  },
  {
   "p1":95,
   "p2":96,
   "gfx":8,
   "flags":1,
   "dx":0,
   "dy":0
  },
  {
   "p1":96,
   "p2":97,
   "gfx":15,
   "flags":1,
   "dx":0,
   "dy":0
  },
  {
   "p1":97,
   "p2":98,
   "gfx":15,
   "flags":1,
   "dx":0,
   "dy":0
  },
  {
   "p1":98,
   "p2":99,
   "gfx":15,
   "flags":1,
   "dx":0,
   "dy":0
  },
  {
   "p1":99,
   "p2":100,
   "gfx":15,
   "flags":1,
   "dx":0,
   "dy":0
  },
  {
   "p1":100,
   "p2":101,
   "gfx":15,
   "flags":1,
   "dx":0,
   "dy":0
  },
  {
   "p1":94,
   "p2":102,
   "gfx":8,
   "flags":1,
   "dx":0,
   "dy":0
  },
  {
   "p1":120,
   "p2":102,
   "gfx":17,
   "flags":1,
   "dx":0,
   "dy":0
  },
  {
   "p1":103,
   "p2":104,
   "gfx":8,
   "flags":1,
   "dx":0,
   "dy":0
  },
  {
   "p1":104,
   "p2":105,
   "gfx":8,
   "flags":1,
   "dx":0,
   "dy":0
  },
  {
   "p1":101,
   "p2":106,
   "gfx":15,
   "flags":1,
   "dx":0,
   "dy":0
  },
  {
   "p1":105,
   "p2":107,
   "gfx":8,
   "flags":1,
   "dx":0,
   "dy":0
  },
  {
   "p1":106,
   "p2":108,
   "gfx":15,
   "flags":1,
   "dx":0,
   "dy":0
  },
  {
   "p1":108,
   "p2":109,
   "gfx":15,
   "flags":1,
   "dx":0,
   "dy":0
  },
  {
   "p1":109,
   "p2":110,
   "gfx":15,
   "flags":1,
   "dx":0,
   "dy":0
  },
  {
   "p1":110,
   "p2":111,
   "gfx":15,
   "flags":1,
   "dx":0,
   "dy":0
  },
  {
   "p1":107,
   "p2":112,
   "gfx":8,
   "flags":1,
   "dx":0,
   "dy":0
  },
  {
   "p1":112,
   "p2":113,
   "gfx":8,
   "flags":1,
   "dx":0,
   "dy":0
  },
  {
   "p1":113,
   "p2":114,
   "gfx":3,
   "flags":1,
   "dx":0,
   "dy":0
  },
  {
   "p1":111,
   "p2":115,
   "gfx":3,
   "flags":1,
   "dx":0,
   "dy":0
  },
  {
   "p1":114,
   "p2":116,
   "gfx":3,
   "flags":1,
   "dx":0,
   "dy":0
  },
  {
   "p1":116,
   "p2":117,
   "gfx":8,
   "flags":1,
   "dx":0,
   "dy":0
  },
  {
   "p1":117,
   "p2":118,
   "gfx":8,
   "flags":1,
   "dx":0,
   "dy":0
  },
  {
   "p1":47,
   "p2":119,
   "gfx":17,
   "flags":1,
   "dx":0,
   "dy":0
  },
  {
   "p1":119,
   "p2":103,
   "gfx":17,
   "flags":1,
   "dx":0,
   "dy":0
  },
  {
   "p1":48,
   "p2":120,
   "gfx":17,
   "flags":1,
   "dx":0,
   "dy":0
  },
  {
   "p1":118,
   "p2":121,
   "gfx":3,
   "flags":1,
   "dx":0,
   "dy":0
  },
  {
   "p1":121,
   "p2":26,
   "gfx":3,
   "flags":1,
   "dx":0,
   "dy":0
  },
  {
   "p1":115,
   "p2":122,
   "gfx":17,
   "flags":1,
   "dx":0,
   "dy":0
  },
  {
   "p1":122,
   "p2":123,
   "gfx":3,
   "flags":1,
   "dx":0,
   "dy":0
  },
  {
   "p1":123,
   "p2":124,
   "gfx":3,
   "flags":1,
   "dx":0,
   "dy":0
  },
  {
   "p1":124,
   "p2":125,
   "gfx":3,
   "flags":1,
   "dx":0,
   "dy":0
  },
  {
   "p1":125,
   "p2":126,
   "gfx":3,
   "flags":1,
   "dx":0,
   "dy":0
  },
  {
   "p1":126,
   "p2":127,
   "gfx":3,
   "flags":1,
   "dx":0,
   "dy":0
  },
  {
   "p1":83,
   "p2":129,
   "gfx":3,
   "flags":1,
   "dx":0,
   "dy":0
  },
  {
   "p1":129,
   "p2":130,
   "gfx":8,
   "flags":1,
   "dx":0,
   "dy":0
  },
  {
   "p1":130,
   "p2":63,
   "gfx":8,
   "flags":1,
   "dx":0,
   "dy":0
  },
  {
   "p1":81,
   "p2":131,
   "gfx":18,
   "flags":1,
   "dx":0,
   "dy":0
  },
  {
   "p1":131,
   "p2":132,
   "gfx":18,
   "flags":1,
   "dx":0,
   "dy":0
  },
  {
   "p1":133,
   "p2":134,
   "gfx":18,
   "flags":1,
   "dx":0,
   "dy":0
  },
  {
   "p1":134,
   "p2":135,
   "gfx":18,
   "flags":1,
   "dx":0,
   "dy":0
  },
  {
   "p1":135,
   "p2":136,
   "gfx":18,
   "flags":1,
   "dx":0,
   "dy":0
  },
  {
   "p1":136,
   "p2":137,
   "gfx":18,
   "flags":1,
   "dx":0,
   "dy":0
  },
  {
   "p1":137,
   "p2":138,
   "gfx":18,
   "flags":1,
   "dx":0,
   "dy":0
  },
  {
   "p1":138,
   "p2":139,
   "gfx":18,
   "flags":1,
   "dx":0,
   "dy":0
  },
  {
   "p1":132,
   "p2":140,
   "gfx":19,
   "flags":1,
   "dx":0,
   "dy":0
  },
  {
   "p1":140,
   "p2":141,
   "gfx":19,
   "flags":1,
   "dx":0,
   "dy":0
  },
  {
   "p1":141,
   "p2":142,
   "gfx":19,
   "flags":1,
   "dx":0,
   "dy":0
  },
  {
   "p1":142,
   "p2":66,
   "gfx":19,
   "flags":1,
   "dx":0,
   "dy":0
  },
  {
   "p1":139,
   "p2":143,
   "gfx":19,
   "flags":1,
   "dx":0,
   "dy":0
  },
  {
   "p1":143,
   "p2":144,
   "gfx":19,
   "flags":1,
   "dx":0,
   "dy":0
  },
  {
   "p1":144,
   "p2":145,
   "gfx":19,
   "flags":1,
   "dx":0,
   "dy":0
  },
  {
   "p1":145,
   "p2":146,
   "gfx":19,
   "flags":1,
   "dx":0,
   "dy":0
  },
  {
   "p1":146,
   "p2":147,
   "gfx":19,
   "flags":1,
   "dx":0,
   "dy":0
  },
  {
   "p1":147,
   "p2":148,
   "gfx":19,
   "flags":1,
   "dx":0,
   "dy":0
  },
  {
   "p1":39,
   "p2":149,
   "gfx":3,
   "flags":1,
   "dx":0,
   "dy":0
  },
  {
   "p1":149,
   "p2":148,
   "gfx":3,
   "flags":1,
   "dx":0,
   "dy":0
  },
  {
   "p1":133,
   "p2":150,
   "gfx":18,
   "flags":1,
   "dx":0,
   "dy":0
  },
  {
   "p1":150,
   "p2":151,
   "gfx":18,
   "flags":1,
   "dx":0,
   "dy":0
  },
  {
   "p1":151,
   "p2":152,
   "gfx":18,
   "flags":1,
   "dx":0,
   "dy":0
  },
  {
   "p1":82,
   "p2":89,
   "gfx":18,
   "flags":1,
   "dx":0,
   "dy":0
  },
  {
   "p1":89,
   "p2":153,
   "gfx":8,
   "flags":1,
   "dx":0,
   "dy":0
  },
  {
   "p1":152,
   "p2":154,
   "gfx":8,
   "flags":1,
   "dx":0,
   "dy":0
  },
  {
   "p1":153,
   "p2":155,
   "gfx":3,
   "flags":1,
   "dx":0,
   "dy":0
  },
  {
   "p1":154,
   "p2":156,
   "gfx":3,
   "flags":1,
   "dx":0,
   "dy":0
  },
  {
   "p1":155,
   "p2":157,
   "gfx":3,
   "flags":1,
   "dx":0,
   "dy":0
  },
  {
   "p1":156,
   "p2":158,
   "gfx":3,
   "flags":1,
   "dx":0,
   "dy":0
  },
  {
   "p1":158,
   "p2":159,
   "gfx":8,
   "flags":1,
   "dx":0,
   "dy":0
  },
  {
   "p1":159,
   "p2":160,
   "gfx":15,
   "flags":1,
   "dx":0,
   "dy":0
  },
  {
   "p1":160,
   "p2":157,
   "gfx":8,
   "flags":1,
   "dx":0,
   "dy":0
  },
  {
   "p1":127,
   "p2":161,
   "gfx":3,
   "flags":1,
   "dx":0,
   "dy":0
  },
  {
   "p1":128,
   "p2":162,
   "gfx":3,
   "flags":1,
   "dx":0,
   "dy":0
  },
  {
   "p1":162,
   "p2":163,
   "gfx":30,
   "flags":1,
   "dx":0,
   "dy":0
  },
  {
   "p1":161,
   "p2":164,
   "gfx":30,
   "flags":1,
   "dx":0,
   "dy":0
  },
  {
   "p1":164,
   "p2":165,
   "gfx":30,
   "flags":1,
   "dx":0,
   "dy":0
  },
  {
   "p1":163,
   "p2":166,
   "gfx":30,
   "flags":1,
   "dx":0,
   "dy":0
  },
  {
   "p1":165,
   "p2":167,
   "gfx":31,
   "flags":1,
   "dx":0,
   "dy":0
  },
  {
   "p1":176,
   "p2":171,
   "gfx":30,
   "flags":1,
   "dx":0,
   "dy":0
  },
  {
   "p1":166,
   "p2":169,
   "gfx":31,
   "flags":1,
   "dx":0,
   "dy":0
  },
  {
   "p1":169,
   "p2":170,
   "gfx":31,
   "flags":1,
   "dx":0,
   "dy":0
  },
  {
   "p1":168,
   "p2":171,
   "gfx":31,
   "flags":1,
   "dx":0,
   "dy":0
  },
  {
   "p1":170,
   "p2":172,
   "gfx":31,
   "flags":1,
   "dx":0,
   "dy":0
  },
  {
   "p1":172,
   "p2":173,
   "gfx":30,
   "flags":1,
   "dx":0,
   "dy":0
  },
  {
   "p1":173,
   "p2":174,
   "gfx":30,
   "flags":1,
   "dx":0,
   "dy":0
  },
  {
   "p1":174,
   "p2":175,
   "gfx":30,
   "flags":1,
   "dx":0,
   "dy":0
  },
  {
   "p1":175,
   "p2":176,
   "gfx":30,
   "flags":1,
   "dx":0,
   "dy":0
  },
  {
   "p1":168,
   "p2":177,
   "gfx":30,
   "flags":1,
   "dx":0,
   "dy":0
  },
  {
   "p1":167,
   "p2":178,
   "gfx":30,
   "flags":1,
   "dx":0,
   "dy":0
  },
  {
   "p1":178,
   "p2":179,
   "gfx":30,
   "flags":1,
   "dx":0,
   "dy":0
  },
  {
   "p1":177,
   "p2":180,
   "gfx":30,
   "flags":1,
   "dx":0,
   "dy":0
  },
  {
   "p1":180,
   "p2":181,
   "gfx":31,
   "flags":1,
   "dx":0,
   "dy":0
  },
  {
   "p1":179,
   "p2":182,
   "gfx":31,
   "flags":1,
   "dx":0,
   "dy":0
  },
  {
   "p1":181,
   "p2":183,
   "gfx":31,
   "flags":1,
   "dx":0,
   "dy":0
  },
  {
   "p1":190,
   "p2":184,
   "gfx":31,
   "flags":1,
   "dx":0,
   "dy":0
  },
  {
   "p1":182,
   "p2":185,
   "gfx":30,
   "flags":1,
   "dx":0,
   "dy":0
  },
  {
   "p1":185,
   "p2":186,
   "gfx":42,
   "flags":11,
   "dx":14,
   "dy":13
  },
  {
   "p1":186,
   "p2":187,
   "gfx":30,
   "flags":1,
   "dx":0,
   "dy":0
  },
  {
   "p1":187,
   "p2":188,
   "gfx":31,
   "flags":1,
   "dx":0,
   "dy":0
  },
  {
   "p1":188,
   "p2":189,
   "gfx":31,
   "flags":1,
   "dx":0,
   "dy":0
  },
  {
   "p1":189,
   "p2":190,
   "gfx":42,
   "flags":27,
   "dx":10,
   "dy":-12
  },
  {
   "p1":183,
   "p2":191,
   "gfx":30,
   "flags":1,
   "dx":0,
   "dy":0
  },
  {
   "p1":191,
   "p2":192,
   "gfx":32,
   "flags":1,
   "dx":0,
   "dy":0
  },
  {
   "p1":192,
   "p2":184,
   "gfx":30,
   "flags":1,
   "dx":0,
   "dy":0
  },
  {
   "p1":185,
   "p2":193,
   "gfx":18,
   "flags":1,
   "dx":0,
   "dy":0
  },
  {
   "p1":186,
   "p2":194,
   "gfx":18,
   "flags":1,
   "dx":0,
   "dy":0
  },
  {
   "p1":194,
   "p2":195,
   "gfx":19,
   "flags":1,
   "dx":0,
   "dy":0
  },
  {
   "p1":193,
   "p2":196,
   "gfx":19,
   "flags":1,
   "dx":0,
   "dy":0
  },
  {
   "p1":196,
   "p2":197,
   "gfx":18,
   "flags":1,
   "dx":0,
   "dy":0
  },
  {
   "p1":195,
   "p2":198,
   "gfx":18,
   "flags":1,
   "dx":0,
   "dy":0
  },
  {
   "p1":197,
   "p2":199,
   "gfx":19,
   "flags":1,
   "dx":0,
   "dy":0
  },
  {
   "p1":198,
   "p2":200,
   "gfx":19,
   "flags":1,
   "dx":0,
   "dy":0
  },
  {
   "p1":199,
   "p2":200,
   "gfx":18,
   "flags":1,
   "dx":0,
   "dy":0
  },
  {
   "p1":178,
   "p2":177,
   "gfx":42,
   "flags":27,
   "dx":10,
   "dy":-12
  },
  {
   "p1":162,
   "p2":161,
   "gfx":42,
   "flags":27,
   "dx":10,
   "dy":-12
  },
  {
   "p1":190,
   "p2":201,
   "gfx":30,
   "flags":1,
   "dx":0,
   "dy":0
  },
  {
   "p1":189,
   "p2":202,
   "gfx":30,
   "flags":1,
   "dx":0,
   "dy":0
  },
  {
   "p1":201,
   "p2":203,
   "gfx":30,
   "flags":1,
   "dx":0,
   "dy":0
  },
  {
   "p1":202,
   "p2":204,
   "gfx":30,
   "flags":1,
   "dx":0,
   "dy":0
  },
  {
   "p1":203,
   "p2":205,
   "gfx":30,
   "flags":1,
   "dx":0,
   "dy":0
  },
  {
   "p1":205,
   "p2":206,
   "gfx":30,
   "flags":1,
   "dx":0,
   "dy":0
  },
  {
   "p1":204,
   "p2":207,
   "gfx":30,
   "flags":1,
   "dx":0,
   "dy":0
  },
  {
   "p1":207,
   "p2":208,
   "gfx":30,
   "flags":1,
   "dx":0,
   "dy":0
  },
  {
   "p1":204,
   "p2":203,
   "gfx":42,
   "flags":27,
   "dx":10,
   "dy":-12
  },
  {
   "p1":206,
   "p2":209,
   "gfx":31,
   "flags":1,
   "dx":0,
   "dy":0
  },
  {
   "p1":208,
   "p2":210,
   "gfx":31,
   "flags":1,
   "dx":0,
   "dy":0
  },
  {
   "p1":211,
   "p2":212,
   "gfx":31,
   "flags":1,
   "dx":0,
   "dy":0
  },
  {
   "p1":213,
   "p2":214,
   "gfx":31,
   "flags":1,
   "dx":0,
   "dy":0
  },
  {
   "p1":215,
   "p2":216,
   "gfx":31,
   "flags":1,
   "dx":0,
   "dy":0
  },
  {
   "p1":217,
   "p2":218,
   "gfx":31,
   "flags":1,
   "dx":0,
   "dy":0
  },
  {
   "p1":213,
   "p2":215,
   "gfx":30,
   "flags":1,
   "dx":0,
   "dy":0
  },
  {
   "p1":211,
   "p2":217,
   "gfx":30,
   "flags":1,
   "dx":0,
   "dy":0
  },
  {
   "p1":210,
   "p2":219,
   "gfx":31,
   "flags":1,
   "dx":0,
   "dy":0
  },
  {
   "p1":209,
   "p2":220,
   "gfx":31,
   "flags":1,
   "dx":0,
   "dy":0
  },
  {
   "p1":219,
   "p2":221,
   "gfx":30,
   "flags":1,
   "dx":0,
   "dy":0
  },
  {
   "p1":220,
   "p2":222,
   "gfx":30,
   "flags":1,
   "dx":0,
   "dy":0
  },
  {
   "p1":214,
   "p2":216,
   "gfx":30,
   "flags":1,
   "dx":0,
   "dy":0
  },
  {
   "p1":212,
   "p2":218,
   "gfx":30,
   "flags":1,
   "dx":0,
   "dy":0
  },
  {
   "p1":222,
   "p2":223,
   "gfx":30,
   "flags":1,
   "dx":0,
   "dy":0
  },
  {
   "p1":221,
   "p2":224,
   "gfx":30,
   "flags":1,
   "dx":0,
   "dy":0
  },
  {
   "p1":224,
   "p2":225,
   "gfx":30,
   "flags":1,
   "dx":0,
   "dy":0
  },
  {
   "p1":223,
   "p2":226,
   "gfx":30,
   "flags":1,
   "dx":0,
   "dy":0
  },
  {
   "p1":227,
   "p2":228,
   "gfx":31,
   "flags":1,
   "dx":0,
   "dy":0
  },
  {
   "p1":236,
   "p2":237,
   "gfx":30,
   "flags":1,
   "dx":0,
   "dy":0
  },
  {
   "p1":229,
   "p2":227,
   "gfx":30,
   "flags":1,
   "dx":0,
   "dy":0
  },
  {
   "p1":235,
   "p2":230,
   "gfx":30,
   "flags":1,
   "dx":0,
   "dy":0
  },
  {
   "p1":228,
   "p2":231,
   "gfx":30,
   "flags":1,
   "dx":0,
   "dy":0
  },
  {
   "p1":229,
   "p2":232,
   "gfx":31,
   "flags":1,
   "dx":0,
   "dy":0
  },
  {
   "p1":231,
   "p2":233,
   "gfx":30,
   "flags":1,
   "dx":0,
   "dy":0
  },
  {
   "p1":232,
   "p2":234,
   "gfx":30,
   "flags":1,
   "dx":0,
   "dy":0
  },
  {
   "p1":226,
   "p2":235,
   "gfx":31,
   "flags":1,
   "dx":0,
   "dy":0
  },
  {
   "p1":225,
   "p2":236,
   "gfx":31,
   "flags":1,
   "dx":0,
   "dy":0
  },
  {
   "p1":238,
   "p2":239,
   "gfx":30,
   "flags":1,
   "dx":0,
   "dy":0
  },
  {
   "p1":240,
   "p2":241,
   "gfx":30,
   "flags":1,
   "dx":0,
   "dy":0
  },
  {
   "p1":230,
   "p2":242,
   "gfx":30,
   "flags":1,
   "dx":0,
   "dy":0
  },
  {
   "p1":242,
   "p2":243,
   "gfx":30,
   "flags":1,
   "dx":0,
   "dy":0
  },
  {
   "p1":237,
   "p2":244,
   "gfx":30,
   "flags":11,
   "dx":13,
   "dy":13
  },
  {
   "p1":244,
   "p2":245,
   "gfx":30,
   "flags":1,
   "dx":0,
   "dy":0
  },
  {
   "p1":245,
   "p2":246,
   "gfx":31,
   "flags":1,
   "dx":0,
   "dy":0
  },
  {
   "p1":240,
   "p2":247,
   "gfx":31,
   "flags":1,
   "dx":0,
   "dy":0
  },
  {
   "p1":238,
   "p2":248,
   "gfx":31,
   "flags":1,
   "dx":0,
   "dy":0
  },
  {
   "p1":233,
   "p2":249,
   "gfx":31,
   "flags":1,
   "dx":0,
   "dy":0
  },
  {
   "p1":234,
   "p2":250,
   "gfx":31,
   "flags":1,
   "dx":0,
   "dy":0
  },
  {
   "p1":243,
   "p2":251,
   "gfx":31,
   "flags":1,
   "dx":0,
   "dy":0
  },
  {
   "p1":249,
   "p2":252,
   "gfx":30,
   "flags":1,
   "dx":0,
   "dy":0
  },
  {
   "p1":250,
   "p2":253,
   "gfx":30,
   "flags":1,
   "dx":0,
   "dy":0
  },
  {
   "p1":248,
   "p2":254,
   "gfx":30,
   "flags":1,
   "dx":0,
   "dy":0
  },
  {
   "p1":247,
   "p2":255,
   "gfx":30,
   "flags":1,
   "dx":0,
   "dy":0
  },
  {
   "p1":239,
   "p2":254,
   "gfx":31,
   "flags":1,
   "dx":0,
   "dy":0
  },
  {
   "p1":241,
   "p2":255,
   "gfx":31,
   "flags":1,
   "dx":0,
   "dy":0
  },
  {
   "p1":251,
   "p2":254,
   "gfx":31,
   "flags":1,
   "dx":0,
   "dy":0
  },
  {
   "p1":246,
   "p2":255,
   "gfx":31,
   "flags":1,
   "dx":0,
   "dy":0
  },
  {
   "p1":252,
   "p2":256,
   "gfx":31,
   "flags":1,
   "dx":0,
   "dy":0
  },
  {
   "p1":253,
   "p2":257,
   "gfx":31,
   "flags":1,
   "dx":0,
   "dy":0
  },
  {
   "p1":256,
   "p2":258,
   "gfx":30,
   "flags":1,
   "dx":0,
   "dy":0
  },
  {
   "p1":257,
   "p2":259,
   "gfx":30,
   "flags":1,
   "dx":0,
   "dy":0
  },
  {
   "p1":258,
   "p2":252,
   "gfx":31,
   "flags":1,
   "dx":0,
   "dy":0
  },
  {
   "p1":259,
   "p2":253,
   "gfx":31,
   "flags":1,
   "dx":0,
   "dy":0
  },
  {
   "p1":250,
   "p2":249,
   "gfx":17,
   "flags":1,
   "dx":0,
   "dy":0
  },
  {
   "p1":246,
   "p2":260,
   "gfx":30,
   "flags":1,
   "dx":0,
   "dy":0
  },
  {
   "p1":251,
   "p2":261,
   "gfx":30,
   "flags":1,
   "dx":0,
   "dy":0
  },
  {
   "p1":260,
   "p2":262,
   "gfx":17,
   "flags":1,
   "dx":0,
   "dy":0
  },
  {
   "p1":262,
   "p2":263,
   "gfx":17,
   "flags":1,
   "dx":0,
   "dy":0
  },
  {
   "p1":263,
   "p2":261,
   "gfx":17,
   "flags":1,
   "dx":0,
   "dy":0
  },
  {
   "p1":244,
   "p2":264,
   "gfx":30,
   "flags":1,
   "dx":0,
   "dy":0
  },
  {
   "p1":237,
   "p2":265,
   "gfx":30,
   "flags":1,
   "dx":0,
   "dy":0
  },
  {
   "p1":267,
   "p2":266,
   "gfx":42,
   "flags":19,
   "dx":12,
   "dy":-12
  },
  {
   "p1":264,
   "p2":268,
   "gfx":31,
   "flags":1,
   "dx":0,
   "dy":0
  },
  {
   "p1":268,
   "p2":269,
   "gfx":19,
   "flags":1,
   "dx":0,
   "dy":0
  },
  {
   "p1":269,
   "p2":270,
   "gfx":19,
   "flags":1,
   "dx":0,
   "dy":0
  },
  {
   "p1":265,
   "p2":271,
   "gfx":19,
   "flags":1,
   "dx":0,
   "dy":0
  },
  {
   "p1":270,
   "p2":272,
   "gfx":18,
   "flags":1,
   "dx":0,
   "dy":0
  },
  {
   "p1":271,
   "p2":273,
   "gfx":18,
   "flags":1,
   "dx":0,
   "dy":0
  },
  {
   "p1":272,
   "p2":6,
   "gfx":18,
   "flags":1,
   "dx":0,
   "dy":0
  }
  ],
 "ob": [
  {
   "x":31042,
   "y":31088,
   "z":0,
   "gfx":33,
   "type":0,
   "flags":0,
   "head":0
  },
  {
   "x":31173,
   "y":31108,
   "z":0,
   "gfx":1,
   "type":0,
   "flags":0,
   "head":0
  },
  {
   "x":31290,
   "y":31108,
   "z":0,
   "gfx":1,
   "type":0,
   "flags":0,
   "head":0
  },
  {
   "x":31400,
   "y":31108,
   "z":0,
   "gfx":1,
   "type":0,
   "flags":0,
   "head":0
  },
  {
   "x":31503,
   "y":31118,
   "z":0,
   "gfx":39,
   "type":0,
   "flags":0,
   "head":0
  },
  {
   "x":31623,
   "y":31102,
   "z":0,
   "gfx":2,
   "type":0,
   "flags":16,
   "head":0
  },
  {
   "x":32081,
   "y":32218,
   "z":0,
   "gfx":22,
   "type":0,
   "flags":16,
   "head":0
  },
  {
   "x":33717,
   "y":32218,
   "z":0,
   "gfx":22,
   "type":0,
   "flags":16,
   "head":0
  },
  {
   "x":33717,
   "y":31618,
   "z":0,
   "gfx":22,
   "type":0,
   "flags":16,
   "head":0
  },
  {
   "x":29757,
   "y":33548,
   "z":0,
   "gfx":22,
   "type":0,
   "flags":16,
   "head":0
  },
  {
   "x":32478,
   "y":31998,
   "z":0,
   "gfx":10,
   "type":1,
   "flags":9,
   "head":0
  },
  {
   "x":32698,
   "y":32158,
   "z":0,
   "gfx":10,
   "type":1,
   "flags":9,
   "head":0
  },
  {
   "x":33482,
   "y":31778,
   "z":0,
   "gfx":10,
   "type":1,
   "flags":9,
   "head":0
  },
  {
   "x":33558,
   "y":32098,
   "z":0,
   "gfx":10,
   "type":1,
   "flags":9,
   "head":0
  },
  {
   "x":30080,
   "y":32128,
   "z":0,
   "gfx":10,
   "type":1,
   "flags":9,
   "head":0
  },
  {
   "x":30861,
   "y":33164,
   "z":80,
   "gfx":23,
   "type":0,
   "flags":0,
   "head":0
  },
  {
   "x":31609,
   "y":32908,
   "z":80,
   "gfx":23,
   "type":0,
   "flags":0,
   "head":0
  },
  {
   "x":31906,
   "y":32924,
   "z":80,
   "gfx":23,
   "type":0,
   "flags":0,
   "head":0
  },
  {
   "x":29563,
   "y":33676,
   "z":80,
   "gfx":23,
   "type":0,
   "flags":0,
   "head":0
  },
  {
   "x":29984,
   "y":31989,
   "z":63,
   "gfx":24,
   "type":0,
   "flags":16,
   "head":0
  },
  {
   "x":30091,
   "y":31920,
   "z":63,
   "gfx":24,
   "type":0,
   "flags":16,
   "head":0
  },
  {
   "x":29904,
   "y":33040,
   "z":63,
   "gfx":24,
   "type":0,
   "flags":16,
   "head":0
  },
  {
   "x":30839,
   "y":33648,
   "z":63,
   "gfx":24,
   "type":0,
   "flags":16,
   "head":0
  },
  {
   "x":29563,
   "y":31568,
   "z":63,
   "gfx":24,
   "type":0,
   "flags":16,
   "head":0
  },
  {
   "x":29310,
   "y":33744,
   "z":63,
   "gfx":24,
   "type":0,
   "flags":16,
   "head":0
  },
  {
   "x":33588,
   "y":32768,
   "z":0,
   "gfx":27,
   "type":2,
   "flags":20,
   "head":0
  },
  {
   "x":35217,
   "y":33356,
   "z":0,
   "gfx":34,
   "type":2,
   "flags":0,
   "head":0
  },
  {
   "x":35062,
   "y":33020,
   "z":0,
   "gfx":35,
   "type":3,
   "flags":80,
   "head":0
  },
  {
   "x":33698,
   "y":31727,
   "z":0,
   "gfx":39,
   "type":0,
   "flags":2,
   "head":0
  },
  {
   "x":33771,
   "y":31727,
   "z":0,
   "gfx":39,
   "type":0,
   "flags":2,
   "head":0
  },
  {
   "x":33424,
   "y":31727,
   "z":0,
   "gfx":39,
   "type":0,
   "flags":2,
   "head":0
  },
  {
   "x":33357,
   "y":31720,
   "z":0,
   "gfx":39,
   "type":0,
   "flags":2,
   "head":0
  },
  {
   "x":29799,
   "y":31606,
   "z":0,
   "gfx":35,
   "type":3,
   "flags":80,
   "head":0
  },
  {
   "x":30915,
   "y":33748,
   "z":0,
   "gfx":35,
   "type":3,
   "flags":80,
   "head":0
  },
  {
   "x":29337,
   "y":33552,
   "z":0,
   "gfx":35,
   "type":3,
   "flags":80,
   "head":0
  },
  {
   "x":30973,
   "y":32922,
   "z":0,
   "gfx":35,
   "type":3,
   "flags":80,
   "head":0
  },
  {
   "x":31512,
   "y":32726,
   "z":0,
   "gfx":35,
   "type":3,
   "flags":80,
   "head":0
  },
  {
   "x":32137,
   "y":33538,
   "z":0,
   "gfx":10,
   "type":1,
   "flags":9,
   "head":0
  },
  {
   "x":30636,
   "y":31774,
   "z":0,
   "gfx":10,
   "type":1,
   "flags":9,
   "head":0
  },
  {
   "x":32091,
   "y":31850,
   "z":0,
   "gfx":22,
   "type":0,
   "flags":16,
   "head":0
  },
  {
   "x":29749,
   "y":33718,
   "z":0,
   "gfx":41,
   "type":2,
   "flags":20,
   "head":0
  },
  {
   "x":30523,
   "y":34212,
   "z":0,
   "gfx":-40,
   "type":0,
   "flags":2,
   "head":0
  },
  {
   "x":31307,
   "y":34284,
   "z":0,
   "gfx":-40,
   "type":0,
   "flags":2,
   "head":0
  },
  {
   "x":31266,
   "y":31992,
   "z":0,
   "gfx":-40,
   "type":0,
   "flags":2,
   "head":0
  },
  {
   "x":29534,
   "y":33876,
   "z":0,
   "gfx":-40,
   "type":0,
   "flags":2,
   "head":0
  }
  ],
 "ceiling":  [
   [
26,26,26,26,26,26,26,26,26,26,26,26,26,26,26,26,26,26,26,26,26,26,26,26,26,26,26,26,26,26,26,26   ],
   [
26,26,26,26,26,26,26,26,26,26,26,26,26,26,26,26,26,26,26,26,26,26,26,26,26,26,26,26,26,26,26,26   ],
   [
26,26,26,26,26,26,26,26,26,26,26,26,26,26,26,26,26,26,26,26,26,26,26,26,26,26,26,26,26,26,26,26   ],
   [
26,26,26,26,26,26,26,26,26,26,26,26,26,26,26,26,26,26,26,26,26,26,26,26,26,26,26,26,26,26,26,26   ],
   [
26,26,26,26,26,26,26,26,26,26,26,26,26,26,26,26,26,26,26,26,26,26,26,26,26,26,26,26,26,26,26,26   ],
   [
26,26,26,26,26,26,26,26,26,26,26,26,26,26,26,26,26,26,26,26,26,26,26,26,26,26,26,26,26,26,26,26   ],
   [
26,26,26,26,26,26,26,26,26,26,26,26,26,26,26,26,26,26,26,26,26,26,26,26,26,26,26,26,26,26,26,26   ],
   [
26,26,26,26,26,26,26,26,26,26,26,26,26,26,26,26,26,26,26,26,26,26,26,26,26,26,26,26,26,26,26,26   ],
   [
26,26,26,26,26,26,26,26,26,26,26,26,26,26,26,26,26,26,26,26,26,26,26,26,26,26,26,26,26,26,26,26   ],
   [
26,26,26,26,26,26,26,26,26,26,26,26,26,26,26,26,26,26,26,26,26,26,26,26,26,26,26,26,26,26,26,26   ],
   [
26,26,26,29,29,29,29,29,29,26,26,26,26,26,26,26,26,26,26,26,26,26,26,26,26,26,26,26,26,26,26,26   ],
   [
26,26,29,29,29,29,29,29,29,26,26,26,26,26,26,26,26,26,26,26,26,26,26,26,26,26,26,26,26,26,26,26   ],
   [
26,26,29,29,26,26,26,26,26,26,26,26,26,26,26,26,26,26,26,26,26,26,26,26,26,26,26,26,26,26,26,26   ],
   [
26,26,29,29,26,26,26,26,26,26,26,26,26,26,26,26,26,26,26,26,26,26,26,26,26,26,26,26,26,26,26,26   ],
   [
26,26,29,29,26,26,26,26,26,26,26,26,26,26,26,26,26,26,26,26,26,26,26,26,26,26,26,26,26,26,26,26   ],
   [
26,26,29,29,26,26,26,26,26,26,26,26,26,26,26,26,26,29,29,29,29,26,26,26,26,26,26,26,26,26,26,26   ],
   [
26,26,29,29,26,26,26,26,26,26,26,9,9,26,26,26,26,29,29,29,29,26,26,26,26,26,26,26,26,26,26,26   ],
   [
26,26,29,29,26,26,26,26,9,26,26,26,26,26,26,26,26,26,29,29,26,26,26,26,26,26,26,26,26,26,26,26   ],
   [
26,26,26,26,26,26,26,26,26,26,26,26,26,26,26,26,26,26,26,26,26,26,26,26,26,26,26,26,26,26,26,26   ],
   [
26,26,26,9,26,26,26,26,26,26,26,26,26,26,26,26,26,26,26,26,26,26,26,26,26,26,26,26,26,26,26,26   ],
   [
26,26,26,26,26,26,26,26,26,26,26,26,26,26,26,26,26,26,26,26,26,26,26,26,26,26,26,26,26,26,26,26   ],
   [
26,26,26,26,26,26,26,26,26,26,26,26,26,26,26,26,26,26,26,26,26,26,26,26,26,26,26,26,26,26,26,26   ],
   [
26,26,26,26,26,26,26,26,26,26,26,26,26,26,26,26,26,26,26,26,26,26,26,26,26,26,26,26,26,26,26,26   ],
   [
26,26,26,26,26,26,26,26,26,26,26,26,26,26,26,26,26,26,26,26,26,26,26,26,26,26,26,26,26,26,26,26   ],
   [
26,26,26,26,26,26,26,26,26,26,26,26,26,26,26,26,26,26,26,26,26,26,26,26,26,26,26,26,26,26,26,26   ],
   [
26,26,26,26,26,26,26,26,26,26,26,26,26,26,26,26,26,26,26,26,26,26,26,26,26,26,26,26,26,26,26,26   ],
   [
26,26,26,26,26,26,26,26,26,26,26,26,26,26,26,26,26,26,26,26,26,26,26,26,26,26,26,26,26,26,26,26   ],
   [
26,26,26,26,26,26,26,26,26,26,26,26,26,26,26,26,26,26,26,26,26,26,26,26,26,26,26,26,26,26,26,26   ],
   [
26,26,26,26,26,26,26,26,26,26,26,26,26,26,26,26,26,26,26,26,26,26,26,26,26,26,26,26,26,26,26,26   ],
   [
26,26,26,26,26,26,26,26,26,26,26,26,26,26,26,26,26,26,26,26,26,26,26,26,26,26,26,26,26,26,26,26   ],
   [
26,26,26,26,26,26,26,26,26,26,26,26,26,26,26,26,26,26,26,26,26,26,26,26,26,26,26,26,26,26,26,26   ],
   [
26,26,26,26,26,26,26,26,26,26,26,26,26,26,26,26,26,26,26,26,26,26,26,26,26,26,26,26,26,26,26,26   ]  ],
 "floor":  [
   [
14,14,14,14,14,14,14,14,14,14,14,14,14,14,14,14,14,14,14,14,14,14,14,14,14,14,14,14,14,14,14,14   ],
   [
14,14,14,14,14,14,14,14,14,14,14,14,14,14,14,14,14,14,14,14,14,14,14,14,14,14,14,14,14,14,14,14   ],
   [
14,14,14,14,14,14,14,14,14,14,14,14,14,14,14,14,14,14,14,14,14,14,14,14,14,14,14,14,14,14,14,14   ],
   [
14,14,14,14,14,14,14,14,14,14,14,14,14,14,14,14,14,14,14,14,14,14,14,14,14,14,14,14,14,14,14,14   ],
   [
14,14,14,14,14,14,14,14,14,14,14,14,14,14,14,14,14,14,14,14,14,14,14,14,14,14,14,14,14,14,14,14   ],
   [
14,14,14,14,14,14,14,14,14,14,14,14,14,14,14,14,14,14,14,14,14,14,14,14,14,14,14,14,14,14,14,14   ],
   [
14,14,14,14,14,14,14,14,14,14,14,14,14,14,14,14,14,14,14,14,14,14,14,14,14,14,14,14,14,14,14,14   ],
   [
14,14,14,14,14,14,14,14,14,14,14,14,14,14,14,14,14,14,14,14,14,14,14,14,14,14,14,14,14,14,14,14   ],
   [
14,14,14,14,14,14,14,14,14,14,14,14,14,14,14,14,14,14,14,14,14,14,14,14,14,14,14,14,14,14,14,14   ],
   [
14,14,14,14,14,14,14,14,14,14,14,14,14,14,14,14,14,14,14,14,14,14,14,14,14,14,14,14,14,14,14,14   ],
   [
14,14,28,28,28,28,28,28,14,14,14,14,14,14,14,14,14,14,14,14,14,14,14,14,14,14,14,14,14,14,14,14   ],
   [
14,14,28,28,28,28,28,28,14,14,14,14,14,14,14,14,14,14,14,14,14,14,14,14,14,14,14,14,14,14,14,14   ],
   [
14,14,28,28,14,14,14,14,14,14,14,14,14,14,14,14,14,14,14,14,14,14,14,14,14,14,14,14,14,14,14,14   ],
   [
14,14,28,28,14,14,14,14,14,14,14,14,14,14,14,14,14,14,14,14,14,28,28,14,14,14,14,14,14,14,14,14   ],
   [
14,14,28,28,14,14,14,14,14,14,14,14,14,14,14,14,14,14,14,14,14,14,14,14,14,14,14,14,14,14,14,14   ],
   [
14,14,28,28,14,14,14,14,14,14,14,14,14,14,14,14,14,14,28,28,14,14,14,14,14,14,14,14,14,14,14,14   ],
   [
14,14,28,28,14,14,14,14,14,14,14,16,16,14,14,14,14,14,28,28,14,14,14,14,28,28,14,14,14,14,14,14   ],
   [
14,14,28,28,14,14,14,14,16,14,14,14,14,14,14,14,14,14,14,14,14,14,14,14,28,28,14,14,14,14,14,14   ],
   [
14,14,14,14,14,14,14,14,14,14,14,14,14,14,14,14,14,14,14,14,14,14,14,14,28,28,28,14,14,14,14,14   ],
   [
14,14,14,16,14,14,14,14,14,14,14,14,14,14,14,14,14,14,14,14,14,14,14,14,28,28,28,14,14,14,14,14   ],
   [
14,14,14,14,14,14,14,14,14,14,14,14,14,14,14,14,14,14,14,14,14,14,14,14,14,14,14,14,14,14,14,14   ],
   [
14,14,14,14,14,14,14,14,14,14,14,14,14,14,14,14,14,14,14,14,14,14,14,14,14,14,14,14,14,14,14,14   ],
   [
14,14,14,14,14,14,14,14,14,14,14,14,14,14,14,14,14,14,14,14,14,14,14,14,14,14,14,14,14,14,14,14   ],
   [
14,14,14,14,14,14,14,14,14,14,14,14,14,14,14,14,14,14,14,14,14,14,14,14,14,14,14,14,14,14,14,14   ],
   [
14,14,14,14,14,14,14,14,14,14,14,14,14,14,14,14,14,14,14,14,14,14,14,14,14,14,14,14,14,14,14,14   ],
   [
14,14,14,14,14,14,14,14,14,14,14,14,14,14,14,14,14,14,14,14,14,14,14,14,14,14,14,14,14,14,14,14   ],
   [
14,14,14,14,14,14,14,14,14,14,14,14,14,14,14,14,14,14,14,14,14,14,14,14,14,14,14,14,14,14,14,14   ],
   [
14,14,14,14,14,14,14,14,14,14,14,14,14,14,14,14,14,14,14,14,14,14,14,14,14,14,14,14,14,14,14,14   ],
   [
14,14,14,14,14,14,14,14,14,14,14,14,14,14,14,14,14,14,14,14,14,14,14,14,14,14,14,14,14,14,14,14   ],
   [
14,14,14,14,14,14,14,14,14,14,14,14,14,14,14,14,14,14,14,14,14,14,14,14,14,14,14,14,14,14,14,14   ],
   [
14,14,14,14,14,14,14,14,14,14,14,14,14,14,14,14,14,14,14,14,14,14,14,14,14,14,14,14,14,14,14,14   ],
   [
14,14,14,14,14,14,14,14,14,14,14,14,14,14,14,14,14,14,14,14,14,14,14,14,14,14,14,14,14,14,14,14   ]  ]
}
