{
 "source_file": "../data/maps/plan4",
 "position": {
  "x":30689,
  "y":34931,
  "h":128
  },
 "gfx": [
  {
   "name":"explo",
   "width":96,
   "height":128,
   "frames":2,
   "type":88,
   "anim":2,
   "t":3
  },
  {
   "name":"sciana-fabr-rur",
   "width":64,
   "height":128,
   "frames":0,
   "type":1,
   "anim":0,
   "t":0
  },
  {
   "name":"sciana-fabr-c",
   "width":64,
   "height":128,
   "frames":0,
   "type":1,
   "anim":0,
   "t":0
  },
  {
   "name":"elektrdrzwi",
   "width":64,
   "height":128,
   "frames":0,
   "type":256,
   "anim":0,
   "t":0
  },
  {
   "name":"bigbang",
   "width":80,
   "height":160,
   "frames":0,
   "type":64,
   "anim":0,
   "t":0
  },
  {
   "name":"grob",
   "width":128,
   "height":64,
   "frames":3,
   "type":4,
   "anim":0,
   "t":0
  },
  {
   "name":"dysk",
   "width":64,
   "height":64,
   "frames":0,
   "type":0,
   "anim":0,
   "t":0
  },
  {
   "name":"fabryka-de-reka",
   "width":64,
   "height":64,
   "frames":0,
   "type":1,
   "anim":0,
   "t":0
  },
  {
   "name":"fabryka-c",
   "width":64,
   "height":64,
   "frames":0,
   "type":1,
   "anim":0,
   "t":0
  },
  {
   "name":"tajniak",
   "width":160,
   "height":96,
   "frames":7,
   "type":4,
   "anim":0,
   "t":0
  },
  {
   "name":"tajniak-pif",
   "width":48,
   "height":96,
   "frames":1,
   "type":0,
   "anim":1,
   "t":0
  },
  {
   "name":"tajniak-boli",
   "width":22,
   "height":96,
   "frames":0,
   "type":1,
   "anim":0,
   "t":0
  },
  {
   "name":"tajniak-trup",
   "width":96,
   "height":96,
   "frames":3,
   "type":8,
   "anim":3,
   "t":3
  },
  {
   "name":"podloga",
   "width":64,
   "height":64,
   "frames":0,
   "type":0,
   "anim":0,
   "t":0
  },
  {
   "name":"podloga-krew",
   "width":64,
   "height":64,
   "frames":0,
   "type":0,
   "anim":0,
   "t":0
  },
  {
   "name":"dach-fabr-bezlam",
   "width":64,
   "height":64,
   "frames":0,
   "type":0,
   "anim":0,
   "t":0
  },
  {
   "name":"dach-fabr",
   "width":64,
   "height":64,
   "frames":0,
   "type":0,
   "anim":0,
   "t":0
  },
  {
   "name":"iskry",
   "width":128,
   "height":64,
   "frames":3,
   "type":0,
   "anim":3,
   "t":0
  },
  {
   "name":"sciana-fabr-dziura",
   "width":64,
   "height":128,
   "frames":0,
   "type":1,
   "anim":0,
   "t":0
  },
  {
   "name":"karabin",
   "width":64,
   "height":34,
   "frames":0,
   "type":0,
   "anim":0,
   "t":0
  },
  {
   "name":"sciana-fabr-dziura-j",
   "width":64,
   "height":64,
   "frames":0,
   "type":1,
   "anim":0,
   "t":0
  },
  {
   "name":"fabryka-lampka",
   "width":64,
   "height":64,
   "frames":0,
   "type":1,
   "anim":0,
   "t":0
  },
  {
   "name":"fabryka-c-blysk",
   "width":128,
   "height":64,
   "frames":1,
   "type":1,
   "anim":1,
   "t":0
  },
  {
   "name":"fabryka-leje",
   "width":128,
   "height":64,
   "frames":1,
   "type":1,
   "anim":1,
   "t":0
  },
  {
   "name":"granat",
   "width":16,
   "height":25,
   "frames":0,
   "type":0,
   "anim":0,
   "t":0
  },
  {
   "name":"fabryka-silnik",
   "width":192,
   "height":64,
   "frames":2,
   "type":1,
   "anim":2,
   "t":0
  },
  {
   "name":"maszyny",
   "width":64,
   "height":64,
   "frames":0,
   "type":256,
   "anim":0,
   "t":0
  },
  {
   "name":"sciana-fabr-snajp",
   "width":64,
   "height":128,
   "frames":0,
   "type":1,
   "anim":0,
   "t":0
  },
  {
   "name":"sciana-fabr-snajp-j",
   "width":22,
   "height":57,
   "frames":0,
   "type":1,
   "anim":0,
   "t":0
  },
  {
   "name":"snajper-ded",
   "width":160,
   "height":96,
   "frames":3,
   "type":8,
   "anim":3,
   "t":1
  },
  {
   "name":"trunek",
   "width":64,
   "height":28,
   "frames":1,
   "type":0,
   "anim":0,
   "t":0
  },
  {
   "name":"sciana-fabr-okno",
   "width":16,
   "height":30,
   "frames":0,
   "type":1,
   "anim":0,
   "t":0
  },
  {
   "name":"fabryka-de",
   "width":0,
   "height":0,
   "frames":0,
   "type":1,
   "anim":0,
   "t":0
  },
  {
   "name":"fabryka-e",
   "width":64,
   "height":64,
   "frames":0,
   "type":1,
   "anim":0,
   "t":0
  },
  {
   "name":"komputer",
   "width":64,
   "height":64,
   "frames":0,
   "type":0,
   "anim":0,
   "t":0
  },
  {
   "name":"fabryka",
   "width":64,
   "height":64,
   "frames":0,
   "type":1,
   "anim":0,
   "t":0
  },
  {
   "name":"sciana-fabr-wyj",
   "width":64,
   "height":128,
   "frames":0,
   "type":1,
   "anim":0,
   "t":0
  },
  {
   "name":"drzwi-fabr",
   "width":128,
   "height":64,
   "frames":0,
   "type":1,
   "anim":0,
   "t":0
  },
  {
   "name":"radar",
   "width":0,
   "height":0,
   "frames":0,
   "type":0,
   "anim":0,
   "t":0
  }
  ],
 "pts": [
  { "x":31222, "y":31238 },
  { "x":31446, "y":31238 },
  { "x":31680, "y":31238 },
  { "x":31935, "y":31238 },
  { "x":32177, "y":31238 },
  { "x":32399, "y":31238 },
  { "x":32622, "y":31238 },
  { "x":32863, "y":31238 },
  { "x":32863, "y":31481 },
  { "x":32863, "y":31706 },
  { "x":31221, "y":31472 },
  { "x":31221, "y":31706 },
  { "x":32863, "y":31931 },
  { "x":31221, "y":31958 },
  { "x":31221, "y":32210 },
  { "x":31221, "y":32444 },
  { "x":31221, "y":32678 },
  { "x":31221, "y":32939 },
  { "x":31228, "y":33182 },
  { "x":31450, "y":32669 },
  { "x":31673, "y":32660 },
  { "x":31889, "y":32669 },
  { "x":31463, "y":33173 },
  { "x":31711, "y":33164 },
  { "x":31909, "y":33164 },
  { "x":32876, "y":32183 },
  { "x":32876, "y":32408 },
  { "x":32882, "y":32642 },
  { "x":32889, "y":32921 },
  { "x":32882, "y":33155 },
  { "x":32634, "y":33155 },
  { "x":32405, "y":33155 },
  { "x":32163, "y":33155 },
  { "x":31906, "y":33418 },
  { "x":32160, "y":33408 },
  { "x":31889, "y":32894 },
  { "x":32099, "y":32885 },
  { "x":32348, "y":32885 },
  { "x":32589, "y":32876 },
  { "x":32589, "y":32660 },
  { "x":32589, "y":32435 },
  { "x":32125, "y":32669 },
  { "x":32131, "y":32444 },
  { "x":32354, "y":32444 },
  { "x":31463, "y":32417 },
  { "x":31692, "y":32417 },
  { "x":31470, "y":32147 },
  { "x":31692, "y":32138 },
  { "x":31883, "y":32417 },
  { "x":31877, "y":32138 },
  { "x":31457, "y":31904 },
  { "x":31673, "y":31904 },
  { "x":31909, "y":31904 },
  { "x":32144, "y":31904 },
  { "x":32354, "y":31913 },
  { "x":32589, "y":31913 },
  { "x":32589, "y":31688 },
  { "x":32589, "y":31481 },
  { "x":32373, "y":31481 },
  { "x":32150, "y":31481 },
  { "x":31909, "y":31481 },
  { "x":31692, "y":31481 },
  { "x":31463, "y":31481 },
  { "x":31457, "y":31697 },
  { "x":31909, "y":31697 },
  { "x":32150, "y":31688 },
  { "x":32160, "y":33618 },
  { "x":31906, "y":33638 },
  { "x":32408, "y":33618 },
  { "x":32655, "y":33618 },
  { "x":32872, "y":33622 },
  { "x":31680, "y":33638 },
  { "x":31475, "y":33638 },
  { "x":31263, "y":33638 },
  { "x":31015, "y":33638 },
  { "x":30789, "y":33638 },
  { "x":30584, "y":33638 },
  { "x":30584, "y":33878 },
  { "x":30577, "y":34128 },
  { "x":30577, "y":34358 },
  { "x":30577, "y":34608 },
  { "x":30584, "y":34838 },
  { "x":30577, "y":35058 },
  { "x":30782, "y":35038 },
  { "x":31001, "y":35048 },
  { "x":31255, "y":35028 },
  { "x":31482, "y":35028 },
  { "x":31687, "y":35028 },
  { "x":31927, "y":35028 },
  { "x":32189, "y":35028 },
  { "x":32429, "y":35028 },
  { "x":32634, "y":35018 },
  { "x":32859, "y":35008 },
  { "x":33113, "y":33611 },
  { "x":33353, "y":33600 },
  { "x":33547, "y":33600 },
  { "x":33742, "y":33600 },
  { "x":33936, "y":33600 },
  { "x":33066, "y":35008 },
  { "x":33286, "y":35008 },
  { "x":33502, "y":35008 },
  { "x":33697, "y":35004 },
  { "x":33891, "y":35008 },
  { "x":31910, "y":33864 },
  { "x":31902, "y":34084 },
  { "x":31902, "y":34315 },
  { "x":31897, "y":34531 },
  { "x":31707, "y":33864 },
  { "x":31490, "y":33864 },
  { "x":31723, "y":34084 },
  { "x":31490, "y":34084 },
  { "x":31715, "y":34535 },
  { "x":31482, "y":34535 },
  { "x":31482, "y":34288 },
  { "x":31249, "y":33864 },
  { "x":30782, "y":33864 },
  { "x":31023, "y":33864 },
  { "x":31241, "y":34095 },
  { "x":31023, "y":34084 },
  { "x":30798, "y":34095 },
  { "x":31241, "y":34535 },
  { "x":31008, "y":34524 },
  { "x":30790, "y":34524 },
  { "x":31235, "y":34297 },
  { "x":30798, "y":34304 },
  { "x":30782, "y":34788 },
  { "x":31015, "y":34788 },
  { "x":31497, "y":34766 },
  { "x":31933, "y":34766 },
  { "x":31707, "y":34766 },
  { "x":32174, "y":33842 },
  { "x":32174, "y":34051 },
  { "x":32166, "y":34293 },
  { "x":32182, "y":34524 },
  { "x":32182, "y":34755 },
  { "x":32415, "y":34755 },
  { "x":32400, "y":34524 },
  { "x":32392, "y":34293 },
  { "x":32392, "y":34051 },
  { "x":32842, "y":34756 },
  { "x":32625, "y":34766 },
  { "x":32617, "y":34524 },
  { "x":32602, "y":34293 },
  { "x":32594, "y":34051 },
  { "x":32594, "y":33853 },
  { "x":32843, "y":34524 },
  { "x":33053, "y":34524 },
  { "x":32835, "y":34293 },
  { "x":33050, "y":34280 },
  { "x":32872, "y":33860 },
  { "x":33050, "y":33860 },
  { "x":33050, "y":34056 },
  { "x":33045, "y":34744 },
  { "x":33355, "y":33842 },
  { "x":33355, "y":34062 },
  { "x":33355, "y":34271 },
  { "x":33534, "y":34282 },
  { "x":33534, "y":34502 },
  { "x":33332, "y":34502 },
  { "x":33713, "y":34502 },
  { "x":33540, "y":34716 },
  { "x":33337, "y":34716 },
  { "x":33718, "y":34716 },
  { "x":34314, "y":34448 },
  { "x":34165, "y":34448 },
  { "x":33541, "y":33798 },
  { "x":33544, "y":33998 },
  { "x":33735, "y":33809 },
  { "x":33735, "y":34007 },
  { "x":33940, "y":33798 },
  { "x":34151, "y":33798 },
  { "x":34151, "y":34028 },
  { "x":33954, "y":34028 },
  { "x":34116, "y":33598 },
  { "x":34328, "y":33598 },
  { "x":33954, "y":34248 },
  { "x":33968, "y":34448 },
  { "x":34165, "y":34248 },
  { "x":33701, "y":35172 },
  { "x":34321, "y":33788 },
  { "x":34321, "y":34028 },
  { "x":34328, "y":34228 },
  { "x":34314, "y":34628 },
  { "x":34307, "y":34808 },
  { "x":34314, "y":34998 },
  { "x":32832, "y":34056 },
  { "x":34311, "y":35208 },
  { "x":33065, "y":35220 },
  { "x":33071, "y":35428 },
  { "x":34321, "y":35408 },
  { "x":33286, "y":35182 },
  { "x":33887, "y":35172 },
  { "x":33501, "y":35184 },
  { "x":34040, "y":35004 },
  { "x":34040, "y":35142 },
  { "x":34049, "y":35316 },
  { "x":33883, "y":35334 },
  { "x":33688, "y":35334 },
  { "x":33070, "y":35616 },
  { "x":34312, "y":35616 },
  { "x":33065, "y":35802 },
  { "x":34316, "y":35784 },
  { "x":33252, "y":35808 },
  { "x":33426, "y":35808 },
  { "x":33607, "y":35802 },
  { "x":33773, "y":35796 },
  { "x":33964, "y":35796 },
  { "x":34138, "y":35784 },
  { "x":33510, "y":35340 },
  { "x":33265, "y":35436 },
  { "x":33501, "y":35520 },
  { "x":33261, "y":35628 },
  { "x":33692, "y":35514 },
  { "x":33875, "y":35520 },
  { "x":34040, "y":35514 },
  { "x":34201, "y":35310 },
  { "x":34201, "y":35094 },
  { "x":34138, "y":35412 },
  { "x":34134, "y":35226 },
  { "x":33688, "y":35634 },
  { "x":33875, "y":35640 },
  { "x":34044, "y":34834 },
  { "x":33892, "y":34822 },
  { "x":33892, "y":34642 },
  { "x":34036, "y":34636 }
  ],
 "seg": [
  {
   "p1":1,
   "p2":2,
   "gfx":21,
   "flags":5,
   "dx":3,
   "dy":0
  },
  {
   "p1":2,
   "p2":3,
   "gfx":32,
   "flags":5,
   "dx":0,
   "dy":0
  },
  {
   "p1":3,
   "p2":4,
   "gfx":2,
   "flags":5,
   "dx":0,
   "dy":0
  },
  {
   "p1":4,
   "p2":5,
   "gfx":32,
   "flags":5,
   "dx":0,
   "dy":0
  },
  {
   "p1":5,
   "p2":6,
   "gfx":2,
   "flags":5,
   "dx":0,
   "dy":0
  },
  {
   "p1":6,
   "p2":7,
   "gfx":32,
   "flags":5,
   "dx":0,
   "dy":0
  },
  {
   "p1":7,
   "p2":8,
   "gfx":2,
   "flags":5,
   "dx":0,
   "dy":0
  },
  {
   "p1":8,
   "p2":9,
   "gfx":19,
   "flags":5,
   "dx":0,
   "dy":0
  },
  {
   "p1":9,
   "p2":10,
   "gfx":3,
   "flags":5,
   "dx":0,
   "dy":0
  },
  {
   "p1":1,
   "p2":11,
   "gfx":19,
   "flags":5,
   "dx":0,
   "dy":0
  },
  {
   "p1":11,
   "p2":12,
   "gfx":3,
   "flags":5,
   "dx":0,
   "dy":0
  },
  {
   "p1":10,
   "p2":13,
   "gfx":3,
   "flags":5,
   "dx":0,
   "dy":0
  },
  {
   "p1":12,
   "p2":14,
   "gfx":3,
   "flags":5,
   "dx":0,
   "dy":0
  },
  {
   "p1":14,
   "p2":15,
   "gfx":19,
   "flags":5,
   "dx":0,
   "dy":0
  },
  {
   "p1":15,
   "p2":16,
   "gfx":3,
   "flags":5,
   "dx":0,
   "dy":0
  },
  {
   "p1":16,
   "p2":17,
   "gfx":19,
   "flags":5,
   "dx":0,
   "dy":0
  },
  {
   "p1":17,
   "p2":18,
   "gfx":3,
   "flags":5,
   "dx":0,
   "dy":0
  },
  {
   "p1":18,
   "p2":19,
   "gfx":19,
   "flags":5,
   "dx":0,
   "dy":0
  },
  {
   "p1":19,
   "p2":23,
   "gfx":21,
   "flags":5,
   "dx":0,
   "dy":0
  },
  {
   "p1":23,
   "p2":24,
   "gfx":32,
   "flags":5,
   "dx":0,
   "dy":0
  },
  {
   "p1":24,
   "p2":25,
   "gfx":2,
   "flags":5,
   "dx":0,
   "dy":0
  },
  {
   "p1":13,
   "p2":26,
   "gfx":19,
   "flags":5,
   "dx":0,
   "dy":0
  },
  {
   "p1":26,
   "p2":27,
   "gfx":3,
   "flags":5,
   "dx":0,
   "dy":0
  },
  {
   "p1":27,
   "p2":28,
   "gfx":19,
   "flags":5,
   "dx":0,
   "dy":0
  },
  {
   "p1":28,
   "p2":29,
   "gfx":3,
   "flags":5,
   "dx":0,
   "dy":0
  },
  {
   "p1":29,
   "p2":30,
   "gfx":19,
   "flags":5,
   "dx":0,
   "dy":0
  },
  {
   "p1":30,
   "p2":31,
   "gfx":21,
   "flags":5,
   "dx":0,
   "dy":0
  },
  {
   "p1":31,
   "p2":32,
   "gfx":32,
   "flags":5,
   "dx":0,
   "dy":0
  },
  {
   "p1":32,
   "p2":33,
   "gfx":2,
   "flags":5,
   "dx":0,
   "dy":0
  },
  {
   "p1":25,
   "p2":34,
   "gfx":3,
   "flags":5,
   "dx":0,
   "dy":0
  },
  {
   "p1":33,
   "p2":35,
   "gfx":3,
   "flags":5,
   "dx":0,
   "dy":0
  },
  {
   "p1":35,
   "p2":67,
   "gfx":3,
   "flags":5,
   "dx":0,
   "dy":0
  },
  {
   "p1":34,
   "p2":68,
   "gfx":3,
   "flags":5,
   "dx":0,
   "dy":0
  },
  {
   "p1":67,
   "p2":69,
   "gfx":2,
   "flags":5,
   "dx":0,
   "dy":0
  },
  {
   "p1":69,
   "p2":70,
   "gfx":21,
   "flags":5,
   "dx":0,
   "dy":0
  },
  {
   "p1":70,
   "p2":71,
   "gfx":32,
   "flags":5,
   "dx":0,
   "dy":0
  },
  {
   "p1":68,
   "p2":72,
   "gfx":2,
   "flags":5,
   "dx":0,
   "dy":0
  },
  {
   "p1":72,
   "p2":73,
   "gfx":32,
   "flags":5,
   "dx":0,
   "dy":0
  },
  {
   "p1":73,
   "p2":74,
   "gfx":21,
   "flags":5,
   "dx":0,
   "dy":0
  },
  {
   "p1":74,
   "p2":75,
   "gfx":32,
   "flags":5,
   "dx":0,
   "dy":0
  },
  {
   "p1":75,
   "p2":76,
   "gfx":2,
   "flags":5,
   "dx":0,
   "dy":0
  },
  {
   "p1":76,
   "p2":77,
   "gfx":2,
   "flags":5,
   "dx":0,
   "dy":0
  },
  {
   "p1":77,
   "p2":78,
   "gfx":3,
   "flags":5,
   "dx":0,
   "dy":0
  },
  {
   "p1":78,
   "p2":79,
   "gfx":19,
   "flags":5,
   "dx":0,
   "dy":0
  },
  {
   "p1":79,
   "p2":80,
   "gfx":19,
   "flags":5,
   "dx":0,
   "dy":0
  },
  {
   "p1":80,
   "p2":81,
   "gfx":3,
   "flags":5,
   "dx":0,
   "dy":0
  },
  {
   "p1":81,
   "p2":82,
   "gfx":19,
   "flags":5,
   "dx":0,
   "dy":0
  },
  {
   "p1":82,
   "p2":83,
   "gfx":3,
   "flags":5,
   "dx":0,
   "dy":0
  },
  {
   "p1":83,
   "p2":84,
   "gfx":21,
   "flags":5,
   "dx":0,
   "dy":0
  },
  {
   "p1":84,
   "p2":85,
   "gfx":2,
   "flags":5,
   "dx":0,
   "dy":0
  },
  {
   "p1":85,
   "p2":86,
   "gfx":2,
   "flags":5,
   "dx":0,
   "dy":0
  },
  {
   "p1":86,
   "p2":87,
   "gfx":21,
   "flags":5,
   "dx":0,
   "dy":0
  },
  {
   "p1":87,
   "p2":88,
   "gfx":32,
   "flags":5,
   "dx":0,
   "dy":0
  },
  {
   "p1":88,
   "p2":89,
   "gfx":2,
   "flags":5,
   "dx":0,
   "dy":0
  },
  {
   "p1":89,
   "p2":90,
   "gfx":21,
   "flags":5,
   "dx":0,
   "dy":0
  },
  {
   "p1":90,
   "p2":91,
   "gfx":32,
   "flags":5,
   "dx":0,
   "dy":0
  },
  {
   "p1":91,
   "p2":92,
   "gfx":21,
   "flags":5,
   "dx":0,
   "dy":0
  },
  {
   "p1":92,
   "p2":93,
   "gfx":32,
   "flags":5,
   "dx":0,
   "dy":0
  },
  {
   "p1":71,
   "p2":94,
   "gfx":32,
   "flags":5,
   "dx":0,
   "dy":0
  },
  {
   "p1":94,
   "p2":95,
   "gfx":21,
   "flags":5,
   "dx":0,
   "dy":0
  },
  {
   "p1":95,
   "p2":96,
   "gfx":2,
   "flags":5,
   "dx":0,
   "dy":0
  },
  {
   "p1":96,
   "p2":97,
   "gfx":2,
   "flags":5,
   "dx":0,
   "dy":0
  },
  {
   "p1":97,
   "p2":98,
   "gfx":21,
   "flags":5,
   "dx":0,
   "dy":0
  },
  {
   "p1":93,
   "p2":99,
   "gfx":2,
   "flags":5,
   "dx":0,
   "dy":0
  },
  {
   "p1":132,
   "p2":139,
   "gfx":2,
   "flags":5,
   "dx":0,
   "dy":0
  },
  {
   "p1":100,
   "p2":101,
   "gfx":2,
   "flags":5,
   "dx":0,
   "dy":0
  },
  {
   "p1":102,
   "p2":103,
   "gfx":2,
   "flags":5,
   "dx":0,
   "dy":0
  },
  {
   "p1":98,
   "p2":174,
   "gfx":2,
   "flags":5,
   "dx":0,
   "dy":0
  },
  {
   "p1":174,
   "p2":175,
   "gfx":2,
   "flags":5,
   "dx":0,
   "dy":0
  },
  {
   "p1":175,
   "p2":180,
   "gfx":19,
   "flags":5,
   "dx":0,
   "dy":0
  },
  {
   "p1":180,
   "p2":181,
   "gfx":3,
   "flags":5,
   "dx":0,
   "dy":0
  },
  {
   "p1":181,
   "p2":182,
   "gfx":19,
   "flags":5,
   "dx":0,
   "dy":0
  },
  {
   "p1":182,
   "p2":164,
   "gfx":19,
   "flags":5,
   "dx":0,
   "dy":0
  },
  {
   "p1":164,
   "p2":183,
   "gfx":3,
   "flags":5,
   "dx":0,
   "dy":0
  },
  {
   "p1":183,
   "p2":184,
   "gfx":19,
   "flags":5,
   "dx":0,
   "dy":0
  },
  {
   "p1":184,
   "p2":185,
   "gfx":19,
   "flags":5,
   "dx":0,
   "dy":0
  },
  {
   "p1":179,
   "p2":192,
   "gfx":2,
   "flags":5,
   "dx":0,
   "dy":0
  },
  {
   "p1":132,
   "p2":133,
   "gfx":19,
   "flags":5,
   "dx":0,
   "dy":0
  },
  {
   "p1":133,
   "p2":138,
   "gfx":2,
   "flags":5,
   "dx":0,
   "dy":0
  },
  {
   "p1":138,
   "p2":139,
   "gfx":3,
   "flags":5,
   "dx":0,
   "dy":0
  },
  {
   "p1":99,
   "p2":188,
   "gfx":37,
   "flags":5,
   "dx":0,
   "dy":0
  },
  {
   "p1":188,
   "p2":189,
   "gfx":19,
   "flags":5,
   "dx":0,
   "dy":0
  },
  {
   "p1":187,
   "p2":190,
   "gfx":3,
   "flags":5,
   "dx":0,
   "dy":0
  },
  {
   "p1":100,
   "p2":191,
   "gfx":3,
   "flags":5,
   "dx":0,
   "dy":0
  },
  {
   "p1":103,
   "p2":192,
   "gfx":3,
   "flags":5,
   "dx":0,
   "dy":0
  },
  {
   "p1":101,
   "p2":193,
   "gfx":3,
   "flags":5,
   "dx":0,
   "dy":0
  },
  {
   "p1":102,
   "p2":179,
   "gfx":3,
   "flags":5,
   "dx":0,
   "dy":0
  },
  {
   "p1":191,
   "p2":193,
   "gfx":2,
   "flags":5,
   "dx":0,
   "dy":0
  },
  {
   "p1":189,
   "p2":199,
   "gfx":3,
   "flags":5,
   "dx":0,
   "dy":0
  },
  {
   "p1":190,
   "p2":200,
   "gfx":3,
   "flags":5,
   "dx":0,
   "dy":0
  },
  {
   "p1":199,
   "p2":201,
   "gfx":3,
   "flags":5,
   "dx":0,
   "dy":0
  },
  {
   "p1":200,
   "p2":202,
   "gfx":3,
   "flags":5,
   "dx":0,
   "dy":0
  },
  {
   "p1":201,
   "p2":203,
   "gfx":2,
   "flags":5,
   "dx":0,
   "dy":0
  },
  {
   "p1":203,
   "p2":204,
   "gfx":32,
   "flags":5,
   "dx":0,
   "dy":0
  },
  {
   "p1":204,
   "p2":205,
   "gfx":2,
   "flags":5,
   "dx":0,
   "dy":0
  },
  {
   "p1":205,
   "p2":206,
   "gfx":32,
   "flags":5,
   "dx":0,
   "dy":0
  },
  {
   "p1":206,
   "p2":207,
   "gfx":2,
   "flags":5,
   "dx":0,
   "dy":0
  },
  {
   "p1":207,
   "p2":208,
   "gfx":32,
   "flags":5,
   "dx":0,
   "dy":0
  },
  {
   "p1":208,
   "p2":202,
   "gfx":2,
   "flags":5,
   "dx":0,
   "dy":0
  },
  {
   "p1":187,
   "p2":185,
   "gfx":3,
   "flags":5,
   "dx":0,
   "dy":0
  },
  {
   "p1":134,
   "p2":135,
   "gfx":9,
   "flags":1,
   "dx":0,
   "dy":0
  },
  {
   "p1":101,
   "p2":102,
   "gfx":36,
   "flags":1,
   "dx":0,
   "dy":0
  },
  {
   "p1":144,
   "p2":186,
   "gfx":36,
   "flags":1,
   "dx":0,
   "dy":0
  },
  {
   "p1":17,
   "p2":20,
   "gfx":36,
   "flags":1,
   "dx":0,
   "dy":0
  },
  {
   "p1":20,
   "p2":21,
   "gfx":36,
   "flags":1,
   "dx":0,
   "dy":0
  },
  {
   "p1":21,
   "p2":22,
   "gfx":36,
   "flags":1,
   "dx":0,
   "dy":0
  },
  {
   "p1":22,
   "p2":36,
   "gfx":9,
   "flags":1,
   "dx":0,
   "dy":0
  },
  {
   "p1":36,
   "p2":37,
   "gfx":36,
   "flags":1,
   "dx":0,
   "dy":0
  },
  {
   "p1":37,
   "p2":38,
   "gfx":26,
   "flags":1,
   "dx":0,
   "dy":0
  },
  {
   "p1":38,
   "p2":39,
   "gfx":36,
   "flags":1,
   "dx":0,
   "dy":0
  },
  {
   "p1":39,
   "p2":40,
   "gfx":9,
   "flags":1,
   "dx":0,
   "dy":0
  },
  {
   "p1":40,
   "p2":41,
   "gfx":9,
   "flags":1,
   "dx":0,
   "dy":0
  },
  {
   "p1":22,
   "p2":42,
   "gfx":34,
   "flags":1,
   "dx":0,
   "dy":0
  },
  {
   "p1":42,
   "p2":43,
   "gfx":9,
   "flags":1,
   "dx":0,
   "dy":0
  },
  {
   "p1":43,
   "p2":44,
   "gfx":26,
   "flags":1,
   "dx":0,
   "dy":0
  },
  {
   "p1":44,
   "p2":41,
   "gfx":36,
   "flags":1,
   "dx":0,
   "dy":0
  },
  {
   "p1":45,
   "p2":46,
   "gfx":22,
   "flags":1,
   "dx":0,
   "dy":0
  },
  {
   "p1":47,
   "p2":48,
   "gfx":36,
   "flags":1,
   "dx":0,
   "dy":0
  },
  {
   "p1":46,
   "p2":49,
   "gfx":26,
   "flags":1,
   "dx":0,
   "dy":0
  },
  {
   "p1":48,
   "p2":50,
   "gfx":26,
   "flags":1,
   "dx":0,
   "dy":0
  },
  {
   "p1":49,
   "p2":50,
   "gfx":9,
   "flags":1,
   "dx":0,
   "dy":0
  },
  {
   "p1":45,
   "p2":47,
   "gfx":9,
   "flags":1,
   "dx":0,
   "dy":0
  },
  {
   "p1":51,
   "p2":52,
   "gfx":36,
   "flags":1,
   "dx":0,
   "dy":0
  },
  {
   "p1":52,
   "p2":53,
   "gfx":36,
   "flags":1,
   "dx":0,
   "dy":0
  },
  {
   "p1":54,
   "p2":55,
   "gfx":26,
   "flags":1,
   "dx":0,
   "dy":0
  },
  {
   "p1":55,
   "p2":56,
   "gfx":36,
   "flags":1,
   "dx":0,
   "dy":0
  },
  {
   "p1":56,
   "p2":57,
   "gfx":9,
   "flags":1,
   "dx":0,
   "dy":0
  },
  {
   "p1":57,
   "p2":58,
   "gfx":9,
   "flags":1,
   "dx":0,
   "dy":0
  },
  {
   "p1":58,
   "p2":59,
   "gfx":36,
   "flags":1,
   "dx":0,
   "dy":0
  },
  {
   "p1":59,
   "p2":60,
   "gfx":22,
   "flags":1,
   "dx":0,
   "dy":0
  },
  {
   "p1":60,
   "p2":61,
   "gfx":36,
   "flags":1,
   "dx":0,
   "dy":0
  },
  {
   "p1":61,
   "p2":62,
   "gfx":22,
   "flags":1,
   "dx":0,
   "dy":0
  },
  {
   "p1":62,
   "p2":63,
   "gfx":36,
   "flags":1,
   "dx":0,
   "dy":0
  },
  {
   "p1":63,
   "p2":64,
   "gfx":9,
   "flags":1,
   "dx":0,
   "dy":0
  },
  {
   "p1":64,
   "p2":51,
   "gfx":9,
   "flags":1,
   "dx":0,
   "dy":0
  },
  {
   "p1":53,
   "p2":65,
   "gfx":24,
   "flags":1,
   "dx":0,
   "dy":0
  },
  {
   "p1":65,
   "p2":61,
   "gfx":23,
   "flags":1,
   "dx":0,
   "dy":0
  },
  {
   "p1":60,
   "p2":66,
   "gfx":24,
   "flags":1,
   "dx":0,
   "dy":0
  },
  {
   "p1":66,
   "p2":54,
   "gfx":23,
   "flags":1,
   "dx":0,
   "dy":0
  },
  {
   "p1":57,
   "p2":10,
   "gfx":36,
   "flags":1,
   "dx":0,
   "dy":0
  },
  {
   "p1":68,
   "p2":104,
   "gfx":9,
   "flags":1,
   "dx":0,
   "dy":0
  },
  {
   "p1":104,
   "p2":105,
   "gfx":9,
   "flags":1,
   "dx":0,
   "dy":0
  },
  {
   "p1":105,
   "p2":106,
   "gfx":9,
   "flags":1,
   "dx":0,
   "dy":0
  },
  {
   "p1":106,
   "p2":107,
   "gfx":9,
   "flags":1,
   "dx":0,
   "dy":0
  },
  {
   "p1":104,
   "p2":108,
   "gfx":26,
   "flags":1,
   "dx":0,
   "dy":0
  },
  {
   "p1":108,
   "p2":109,
   "gfx":26,
   "flags":1,
   "dx":0,
   "dy":0
  },
  {
   "p1":105,
   "p2":110,
   "gfx":26,
   "flags":1,
   "dx":0,
   "dy":0
  },
  {
   "p1":110,
   "p2":111,
   "gfx":34,
   "flags":1,
   "dx":0,
   "dy":0
  },
  {
   "p1":107,
   "p2":112,
   "gfx":36,
   "flags":1,
   "dx":0,
   "dy":0
  },
  {
   "p1":112,
   "p2":113,
   "gfx":36,
   "flags":1,
   "dx":0,
   "dy":0
  },
  {
   "p1":113,
   "p2":114,
   "gfx":9,
   "flags":1,
   "dx":0,
   "dy":0
  },
  {
   "p1":114,
   "p2":111,
   "gfx":23,
   "flags":1,
   "dx":0,
   "dy":0
  },
  {
   "p1":109,
   "p2":73,
   "gfx":9,
   "flags":1,
   "dx":0,
   "dy":0
  },
  {
   "p1":74,
   "p2":115,
   "gfx":9,
   "flags":1,
   "dx":0,
   "dy":0
  },
  {
   "p1":76,
   "p2":116,
   "gfx":9,
   "flags":1,
   "dx":0,
   "dy":0
  },
  {
   "p1":116,
   "p2":117,
   "gfx":22,
   "flags":1,
   "dx":0,
   "dy":0
  },
  {
   "p1":117,
   "p2":115,
   "gfx":26,
   "flags":1,
   "dx":0,
   "dy":0
  },
  {
   "p1":118,
   "p2":119,
   "gfx":36,
   "flags":1,
   "dx":0,
   "dy":0
  },
  {
   "p1":119,
   "p2":120,
   "gfx":22,
   "flags":1,
   "dx":0,
   "dy":0
  },
  {
   "p1":121,
   "p2":122,
   "gfx":26,
   "flags":1,
   "dx":0,
   "dy":0
  },
  {
   "p1":122,
   "p2":123,
   "gfx":36,
   "flags":1,
   "dx":0,
   "dy":0
  },
  {
   "p1":121,
   "p2":124,
   "gfx":9,
   "flags":1,
   "dx":0,
   "dy":0
  },
  {
   "p1":124,
   "p2":118,
   "gfx":24,
   "flags":1,
   "dx":0,
   "dy":0
  },
  {
   "p1":120,
   "p2":125,
   "gfx":9,
   "flags":1,
   "dx":0,
   "dy":0
  },
  {
   "p1":125,
   "p2":123,
   "gfx":9,
   "flags":1,
   "dx":0,
   "dy":0
  },
  {
   "p1":84,
   "p2":126,
   "gfx":9,
   "flags":1,
   "dx":0,
   "dy":0
  },
  {
   "p1":85,
   "p2":127,
   "gfx":9,
   "flags":1,
   "dx":0,
   "dy":0
  },
  {
   "p1":87,
   "p2":128,
   "gfx":9,
   "flags":1,
   "dx":0,
   "dy":0
  },
  {
   "p1":89,
   "p2":129,
   "gfx":9,
   "flags":1,
   "dx":0,
   "dy":0
  },
  {
   "p1":126,
   "p2":127,
   "gfx":36,
   "flags":1,
   "dx":0,
   "dy":0
  },
  {
   "p1":128,
   "p2":130,
   "gfx":36,
   "flags":1,
   "dx":0,
   "dy":0
  },
  {
   "p1":130,
   "p2":129,
   "gfx":26,
   "flags":1,
   "dx":0,
   "dy":0
  },
  {
   "p1":67,
   "p2":131,
   "gfx":9,
   "flags":1,
   "dx":0,
   "dy":0
  },
  {
   "p1":131,
   "p2":132,
   "gfx":9,
   "flags":1,
   "dx":0,
   "dy":0
  },
  {
   "p1":133,
   "p2":134,
   "gfx":9,
   "flags":1,
   "dx":0,
   "dy":0
  },
  {
   "p1":135,
   "p2":136,
   "gfx":22,
   "flags":1,
   "dx":0,
   "dy":0
  },
  {
   "p1":134,
   "p2":137,
   "gfx":26,
   "flags":1,
   "dx":0,
   "dy":0
  },
  {
   "p1":136,
   "p2":137,
   "gfx":9,
   "flags":1,
   "dx":0,
   "dy":0
  },
  {
   "p1":140,
   "p2":146,
   "gfx":33,
   "flags":1,
   "dx":0,
   "dy":0
  },
  {
   "p1":34,
   "p2":35,
   "gfx":38,
   "flags":27,
   "dx":15,
   "dy":0
  },
  {
   "p1":141,
   "p2":140,
   "gfx":36,
   "flags":1,
   "dx":0,
   "dy":0
  },
  {
   "p1":141,
   "p2":142,
   "gfx":9,
   "flags":1,
   "dx":0,
   "dy":0
  },
  {
   "p1":143,
   "p2":144,
   "gfx":9,
   "flags":1,
   "dx":0,
   "dy":0
  },
  {
   "p1":144,
   "p2":145,
   "gfx":9,
   "flags":1,
   "dx":0,
   "dy":0
  },
  {
   "p1":142,
   "p2":146,
   "gfx":36,
   "flags":1,
   "dx":0,
   "dy":0
  },
  {
   "p1":146,
   "p2":147,
   "gfx":36,
   "flags":1,
   "dx":0,
   "dy":0
  },
  {
   "p1":148,
   "p2":186,
   "gfx":9,
   "flags":1,
   "dx":0,
   "dy":0
  },
  {
   "p1":148,
   "p2":149,
   "gfx":26,
   "flags":1,
   "dx":0,
   "dy":0
  },
  {
   "p1":145,
   "p2":150,
   "gfx":36,
   "flags":1,
   "dx":0,
   "dy":0
  },
  {
   "p1":150,
   "p2":151,
   "gfx":22,
   "flags":1,
   "dx":0,
   "dy":0
  },
  {
   "p1":149,
   "p2":152,
   "gfx":9,
   "flags":1,
   "dx":0,
   "dy":0
  },
  {
   "p1":152,
   "p2":151,
   "gfx":9,
   "flags":1,
   "dx":0,
   "dy":0
  },
  {
   "p1":147,
   "p2":153,
   "gfx":9,
   "flags":1,
   "dx":0,
   "dy":0
  },
  {
   "p1":153,
   "p2":99,
   "gfx":9,
   "flags":1,
   "dx":0,
   "dy":0
  },
  {
   "p1":95,
   "p2":154,
   "gfx":9,
   "flags":1,
   "dx":0,
   "dy":0
  },
  {
   "p1":154,
   "p2":155,
   "gfx":9,
   "flags":1,
   "dx":0,
   "dy":0
  },
  {
   "p1":155,
   "p2":156,
   "gfx":9,
   "flags":1,
   "dx":0,
   "dy":0
  },
  {
   "p1":156,
   "p2":157,
   "gfx":36,
   "flags":1,
   "dx":0,
   "dy":0
  },
  {
   "p1":157,
   "p2":158,
   "gfx":9,
   "flags":1,
   "dx":0,
   "dy":0
  },
  {
   "p1":158,
   "p2":159,
   "gfx":36,
   "flags":1,
   "dx":0,
   "dy":0
  },
  {
   "p1":158,
   "p2":160,
   "gfx":34,
   "flags":1,
   "dx":0,
   "dy":0
  },
  {
   "p1":161,
   "p2":162,
   "gfx":36,
   "flags":1,
   "dx":0,
   "dy":0
  },
  {
   "p1":161,
   "p2":163,
   "gfx":36,
   "flags":1,
   "dx":0,
   "dy":0
  },
  {
   "p1":162,
   "p2":159,
   "gfx":9,
   "flags":1,
   "dx":0,
   "dy":0
  },
  {
   "p1":165,
   "p2":164,
   "gfx":36,
   "flags":1,
   "dx":0,
   "dy":0
  },
  {
   "p1":96,
   "p2":166,
   "gfx":9,
   "flags":1,
   "dx":0,
   "dy":0
  },
  {
   "p1":166,
   "p2":167,
   "gfx":9,
   "flags":1,
   "dx":0,
   "dy":0
  },
  {
   "p1":97,
   "p2":168,
   "gfx":9,
   "flags":27,
   "dx":-13,
   "dy":14
  },
  {
   "p1":168,
   "p2":169,
   "gfx":9,
   "flags":1,
   "dx":0,
   "dy":0
  },
  {
   "p1":167,
   "p2":169,
   "gfx":36,
   "flags":1,
   "dx":0,
   "dy":0
  },
  {
   "p1":166,
   "p2":168,
   "gfx":36,
   "flags":1,
   "dx":0,
   "dy":0
  },
  {
   "p1":170,
   "p2":171,
   "gfx":36,
   "flags":1,
   "dx":0,
   "dy":0
  },
  {
   "p1":172,
   "p2":173,
   "gfx":34,
   "flags":1,
   "dx":0,
   "dy":0
  },
  {
   "p1":170,
   "p2":173,
   "gfx":9,
   "flags":1,
   "dx":0,
   "dy":0
  },
  {
   "p1":171,
   "p2":172,
   "gfx":9,
   "flags":1,
   "dx":0,
   "dy":0
  },
  {
   "p1":173,
   "p2":176,
   "gfx":9,
   "flags":1,
   "dx":0,
   "dy":0
  },
  {
   "p1":176,
   "p2":177,
   "gfx":9,
   "flags":1,
   "dx":0,
   "dy":0
  },
  {
   "p1":176,
   "p2":178,
   "gfx":26,
   "flags":1,
   "dx":0,
   "dy":0
  },
  {
   "p1":177,
   "p2":165,
   "gfx":36,
   "flags":1,
   "dx":0,
   "dy":0
  },
  {
   "p1":165,
   "p2":178,
   "gfx":9,
   "flags":1,
   "dx":0,
   "dy":0
  },
  {
   "p1":163,
   "p2":160,
   "gfx":9,
   "flags":1,
   "dx":0,
   "dy":0
  },
  {
   "p1":142,
   "p2":143,
   "gfx":9,
   "flags":1,
   "dx":0,
   "dy":0
  },
  {
   "p1":150,
   "p2":71,
   "gfx":38,
   "flags":19,
   "dx":0,
   "dy":-15
  },
  {
   "p1":193,
   "p2":179,
   "gfx":36,
   "flags":27,
   "dx":14,
   "dy":-1
  },
  {
   "p1":103,
   "p2":194,
   "gfx":36,
   "flags":1,
   "dx":0,
   "dy":0
  },
  {
   "p1":194,
   "p2":195,
   "gfx":9,
   "flags":1,
   "dx":0,
   "dy":0
  },
  {
   "p1":219,
   "p2":195,
   "gfx":36,
   "flags":1,
   "dx":0,
   "dy":0
  },
  {
   "p1":192,
   "p2":197,
   "gfx":9,
   "flags":1,
   "dx":0,
   "dy":0
  },
  {
   "p1":218,
   "p2":196,
   "gfx":36,
   "flags":1,
   "dx":0,
   "dy":0
  },
  {
   "p1":197,
   "p2":198,
   "gfx":26,
   "flags":1,
   "dx":0,
   "dy":0
  },
  {
   "p1":198,
   "p2":209,
   "gfx":36,
   "flags":1,
   "dx":0,
   "dy":0
  },
  {
   "p1":189,
   "p2":210,
   "gfx":22,
   "flags":1,
   "dx":0,
   "dy":0
  },
  {
   "p1":209,
   "p2":211,
   "gfx":9,
   "flags":1,
   "dx":0,
   "dy":0
  },
  {
   "p1":210,
   "p2":212,
   "gfx":9,
   "flags":1,
   "dx":0,
   "dy":0
  },
  {
   "p1":199,
   "p2":212,
   "gfx":34,
   "flags":1,
   "dx":0,
   "dy":0
  },
  {
   "p1":211,
   "p2":213,
   "gfx":36,
   "flags":1,
   "dx":0,
   "dy":0
  },
  {
   "p1":220,
   "p2":221,
   "gfx":36,
   "flags":1,
   "dx":0,
   "dy":0
  },
  {
   "p1":214,
   "p2":215,
   "gfx":36,
   "flags":1,
   "dx":0,
   "dy":0
  },
  {
   "p1":190,
   "p2":216,
   "gfx":9,
   "flags":1,
   "dx":0,
   "dy":0
  },
  {
   "p1":187,
   "p2":217,
   "gfx":9,
   "flags":1,
   "dx":0,
   "dy":0
  },
  {
   "p1":216,
   "p2":187,
   "gfx":36,
   "flags":1,
   "dx":0,
   "dy":0
  },
  {
   "p1":217,
   "p2":185,
   "gfx":36,
   "flags":1,
   "dx":0,
   "dy":0
  },
  {
   "p1":215,
   "p2":218,
   "gfx":9,
   "flags":1,
   "dx":0,
   "dy":0
  },
  {
   "p1":196,
   "p2":219,
   "gfx":9,
   "flags":1,
   "dx":0,
   "dy":0
  },
  {
   "p1":208,
   "p2":200,
   "gfx":22,
   "flags":1,
   "dx":0,
   "dy":0
  },
  {
   "p1":213,
   "p2":220,
   "gfx":9,
   "flags":1,
   "dx":0,
   "dy":0
  },
  {
   "p1":214,
   "p2":221,
   "gfx":9,
   "flags":1,
   "dx":0,
   "dy":0
  },
  {
   "p1":194,
   "p2":222,
   "gfx":9,
   "flags":1,
   "dx":0,
   "dy":0
  },
  {
   "p1":103,
   "p2":223,
   "gfx":9,
   "flags":1,
   "dx":0,
   "dy":0
  },
  {
   "p1":223,
   "p2":224,
   "gfx":9,
   "flags":1,
   "dx":0,
   "dy":0
  },
  {
   "p1":222,
   "p2":225,
   "gfx":9,
   "flags":1,
   "dx":0,
   "dy":0
  },
  {
   "p1":224,
   "p2":225,
   "gfx":36,
   "flags":1,
   "dx":0,
   "dy":0
  },
  {
   "p1":99,
   "p2":100,
   "gfx":36,
   "flags":1,
   "dx":0,
   "dy":0
  }
  ],
 "ob": [
  {
   "x":34238,
   "y":32268,
   "z":0,
   "gfx":18,
   "type":0,
   "flags":0,
   "head":0
  },
  {
   "x":34309,
   "y":32248,
   "z":0,
   "gfx":18,
   "type":0,
   "flags":0,
   "head":0
  },
  {
   "x":34401,
   "y":32428,
   "z":0,
   "gfx":18,
   "type":0,
   "flags":0,
   "head":0
  },
  {
   "x":34309,
   "y":32628,
   "z":0,
   "gfx":36,
   "type":0,
   "flags":0,
   "head":0
  },
  {
   "x":34090,
   "y":32568,
   "z":0,
   "gfx":8,
   "type":0,
   "flags":0,
   "head":0
  },
  {
   "x":34026,
   "y":32338,
   "z":0,
   "gfx":4,
   "type":0,
   "flags":0,
   "head":0
  },
  {
   "x":31251,
   "y":34082,
   "z":80,
   "gfx":18,
   "type":0,
   "flags":0,
   "head":0
  },
  {
   "x":31905,
   "y":33168,
   "z":192,
   "gfx":18,
   "type":0,
   "flags":0,
   "head":0
  },
  {
   "x":32424,
   "y":34750,
   "z":80,
   "gfx":18,
   "type":0,
   "flags":0,
   "head":0
  },
  {
   "x":33744,
   "y":34001,
   "z":80,
   "gfx":18,
   "type":0,
   "flags":0,
   "head":0
  },
  {
   "x":31373,
   "y":33691,
   "z":100,
   "gfx":30,
   "type":19,
   "flags":256,
   "head":0
  },
  {
   "x":31381,
   "y":34967,
   "z":100,
   "gfx":30,
   "type":19,
   "flags":256,
   "head":0
  },
  {
   "x":32516,
   "y":33669,
   "z":100,
   "gfx":30,
   "type":19,
   "flags":256,
   "head":0
  },
  {
   "x":32067,
   "y":34981,
   "z":100,
   "gfx":30,
   "type":19,
   "flags":256,
   "head":0
  },
  {
   "x":34267,
   "y":33704,
   "z":100,
   "gfx":30,
   "type":19,
   "flags":256,
   "head":0
  },
  {
   "x":34267,
   "y":34716,
   "z":100,
   "gfx":30,
   "type":19,
   "flags":256,
   "head":0
  },
  {
   "x":33119,
   "y":35301,
   "z":100,
   "gfx":30,
   "type":19,
   "flags":256,
   "head":0
  },
  {
   "x":31275,
   "y":33051,
   "z":100,
   "gfx":30,
   "type":19,
   "flags":256,
   "head":0
  },
  {
   "x":32831,
   "y":33040,
   "z":100,
   "gfx":30,
   "type":19,
   "flags":256,
   "head":0
  },
  {
   "x":31345,
   "y":31286,
   "z":100,
   "gfx":30,
   "type":19,
   "flags":256,
   "head":0
  },
  {
   "x":31816,
   "y":33968,
   "z":0,
   "gfx":31,
   "type":2,
   "flags":16,
   "head":0
  },
  {
   "x":32724,
   "y":34160,
   "z":0,
   "gfx":31,
   "type":2,
   "flags":16,
   "head":0
  },
  {
   "x":31341,
   "y":32280,
   "z":0,
   "gfx":31,
   "type":2,
   "flags":16,
   "head":0
  },
  {
   "x":32747,
   "y":31358,
   "z":0,
   "gfx":31,
   "type":2,
   "flags":16,
   "head":0
  },
  {
   "x":33593,
   "y":35078,
   "z":0,
   "gfx":31,
   "type":2,
   "flags":16,
   "head":0
  },
  {
   "x":33633,
   "y":33706,
   "z":0,
   "gfx":31,
   "type":2,
   "flags":16,
   "head":0
  },
  {
   "x":32951,
   "y":34616,
   "z":0,
   "gfx":35,
   "type":0,
   "flags":0,
   "head":0
  },
  {
   "x":32307,
   "y":34386,
   "z":0,
   "gfx":25,
   "type":2,
   "flags":20,
   "head":0
  },
  {
   "x":34128,
   "y":34120,
   "z":0,
   "gfx":25,
   "type":2,
   "flags":20,
   "head":0
  },
  {
   "x":32050,
   "y":33686,
   "z":0,
   "gfx":10,
   "type":1,
   "flags":9,
   "head":0
  },
  {
   "x":31357,
   "y":33980,
   "z":0,
   "gfx":10,
   "type":1,
   "flags":9,
   "head":0
  },
  {
   "x":33831,
   "y":33882,
   "z":0,
   "gfx":10,
   "type":1,
   "flags":9,
   "head":0
  },
  {
   "x":33346,
   "y":35310,
   "z":0,
   "gfx":10,
   "type":1,
   "flags":9,
   "head":0
  },
  {
   "x":32377,
   "y":32062,
   "z":0,
   "gfx":10,
   "type":1,
   "flags":9,
   "head":0
  },
  {
   "x":32713,
   "y":31362,
   "z":0,
   "gfx":10,
   "type":1,
   "flags":9,
   "head":0
  },
  {
   "x":32726,
   "y":31578,
   "z":0,
   "gfx":7,
   "type":2,
   "flags":20,
   "head":0
  },
  {
   "x":32328,
   "y":33743,
   "z":0,
   "gfx":39,
   "type":2,
   "flags":20,
   "head":0
  },
  {
   "x":31039,
   "y":34323,
   "z":192,
   "gfx":-27,
   "type":0,
   "flags":0,
   "head":0
  },
  {
   "x":32882,
   "y":33993,
   "z":192,
   "gfx":-27,
   "type":0,
   "flags":0,
   "head":0
  },
  {
   "x":34133,
   "y":34125,
   "z":192,
   "gfx":-27,
   "type":0,
   "flags":0,
   "head":0
  },
  {
   "x":33791,
   "y":35264,
   "z":192,
   "gfx":-27,
   "type":0,
   "flags":0,
   "head":0
  },
  {
   "x":31723,
   "y":35024,
   "z":192,
   "gfx":-27,
   "type":0,
   "flags":0,
   "head":0
  },
  {
   "x":32291,
   "y":32734,
   "z":192,
   "gfx":-27,
   "type":0,
   "flags":0,
   "head":0
  },
  {
   "x":32353,
   "y":31777,
   "z":192,
   "gfx":-27,
   "type":0,
   "flags":0,
   "head":0
  }
  ],
 "ceiling":  [
   [
16,16,16,16,16,16,16,16,16,16,16,16,16,16,16,16,16,16,16,16,16,16,16,16,16,16,16,16,16,16,16,16   ],
   [
16,16,16,16,16,16,16,16,16,16,16,16,16,16,16,16,16,16,16,16,16,16,16,16,16,16,16,16,16,16,16,16   ],
   [
16,16,16,16,16,16,16,16,16,16,16,16,16,16,16,16,16,16,16,16,16,16,16,16,16,16,16,16,16,16,16,16   ],
   [
16,16,16,16,16,16,16,16,16,16,16,16,16,16,16,16,16,16,16,16,16,16,16,16,16,16,16,16,16,16,16,16   ],
   [
16,16,16,16,16,16,16,16,16,16,16,16,16,16,16,16,16,16,16,16,16,16,16,16,16,16,16,16,16,16,16,16   ],
   [
16,16,16,16,16,16,16,16,16,16,16,16,16,16,16,16,16,16,16,16,16,16,16,16,16,16,16,16,16,16,16,16   ],
   [
16,16,16,16,16,16,16,16,16,16,16,16,16,16,16,16,16,16,16,16,16,16,16,16,16,16,16,16,16,16,16,16   ],
   [
16,16,16,16,16,16,16,16,16,16,16,16,16,16,16,16,16,16,16,16,16,16,16,16,16,16,16,16,16,16,16,16   ],
   [
16,16,16,16,16,16,16,16,16,16,16,16,16,16,16,16,16,16,16,16,16,16,16,16,16,16,16,16,16,16,16,16   ],
   [
16,16,16,16,16,16,16,16,16,16,16,16,16,16,16,16,16,16,16,16,16,16,16,16,16,16,16,16,16,16,16,16   ],
   [
16,16,16,16,16,16,16,16,16,16,16,16,16,16,16,16,16,16,16,16,16,16,16,16,16,16,16,16,16,16,16,16   ],
   [
16,16,16,16,16,16,16,16,16,16,16,17,17,17,17,17,16,16,16,16,16,16,16,16,16,16,16,16,16,16,16,16   ],
   [
16,16,16,16,16,16,16,16,16,16,16,16,16,17,16,16,16,16,16,16,16,16,16,16,16,16,16,16,16,16,16,16   ],
   [
16,16,16,16,16,16,16,16,16,16,16,16,17,16,16,16,16,16,16,16,16,16,16,16,16,16,16,16,16,16,16,16   ],
   [
16,16,16,16,16,16,16,16,16,16,16,16,16,17,16,16,16,16,16,16,16,16,16,16,16,16,16,16,16,16,16,16   ],
   [
16,16,16,16,16,16,16,16,16,16,16,16,17,16,16,16,16,16,16,16,16,16,16,16,16,16,16,16,16,16,16,16   ],
   [
16,16,16,16,16,16,16,16,16,16,16,17,17,17,17,17,16,16,16,16,16,16,16,16,16,16,16,16,16,16,16,16   ],
   [
16,16,16,16,16,16,16,16,16,16,16,16,16,16,16,16,16,16,16,16,16,16,16,16,16,16,16,16,16,16,16,16   ],
   [
16,16,16,16,16,16,16,16,16,16,16,16,16,16,16,16,16,16,16,16,16,16,16,16,16,16,16,16,16,16,16,16   ],
   [
16,16,16,16,16,16,16,16,16,16,16,16,16,16,16,16,16,16,16,16,16,16,16,16,16,16,16,16,16,16,16,16   ],
   [
16,16,16,16,16,16,16,16,16,16,16,16,16,16,16,16,16,16,16,16,16,16,16,16,16,16,16,16,16,16,16,16   ],
   [
16,16,16,16,16,16,16,16,16,17,17,17,16,16,16,17,17,17,16,16,16,16,16,16,16,16,16,16,16,16,16,16   ],
   [
16,16,16,16,16,16,16,16,16,17,16,17,17,17,17,17,16,17,16,16,16,16,16,16,16,16,16,16,16,16,16,16   ],
   [
16,16,16,16,16,16,16,16,16,17,17,17,16,16,16,17,17,17,16,16,16,16,16,16,16,16,16,16,16,16,16,16   ],
   [
16,16,16,16,16,16,16,16,16,16,16,16,16,16,16,16,16,16,16,16,16,16,16,16,16,16,16,16,16,16,16,16   ],
   [
16,16,16,16,16,16,16,16,16,16,16,16,16,16,16,16,16,16,16,16,16,16,16,16,16,16,16,16,16,16,16,16   ],
   [
16,16,16,16,16,16,16,16,16,16,16,16,16,16,16,16,16,16,16,16,16,16,16,16,16,16,16,16,16,16,16,16   ],
   [
16,16,16,16,16,16,16,16,16,16,16,16,16,16,16,16,16,16,16,16,16,16,16,16,16,16,16,16,16,16,16,16   ],
   [
16,16,16,16,16,16,16,16,16,16,16,16,16,16,16,16,16,16,16,16,16,16,16,16,16,16,16,16,16,16,16,16   ],
   [
16,16,16,16,16,16,16,16,16,16,16,16,16,16,16,16,16,16,16,16,16,16,16,16,16,16,16,16,16,16,16,16   ],
   [
16,16,16,16,16,16,16,16,16,16,16,16,16,16,16,16,16,16,16,16,16,16,16,16,16,16,16,16,16,16,16,16   ],
   [
16,16,16,16,16,16,16,16,16,16,16,16,16,16,16,16,16,16,16,16,16,16,16,16,16,16,16,16,16,16,16,16   ]  ],
 "floor":  [
   [
14,14,14,14,14,14,14,14,14,14,14,14,14,14,14,14,14,14,14,14,14,14,14,14,14,14,14,14,14,14,14,14   ],
   [
14,14,14,14,14,14,14,14,14,14,14,14,14,14,14,14,14,14,14,14,14,14,14,14,14,14,14,14,14,14,14,14   ],
   [
14,14,14,14,14,14,14,14,14,14,14,14,14,14,14,14,14,14,14,14,14,14,14,14,14,14,14,14,14,14,14,14   ],
   [
14,14,14,14,14,14,14,14,14,14,14,14,14,14,14,14,14,14,14,14,14,14,14,14,14,14,14,14,14,14,14,14   ],
   [
14,14,14,14,14,14,14,14,14,14,14,14,14,14,14,14,14,14,14,14,14,14,14,14,14,14,14,14,14,14,14,14   ],
   [
14,14,14,14,14,14,14,14,14,14,14,14,14,14,14,14,14,14,14,14,14,14,14,14,14,14,14,14,14,14,14,14   ],
   [
14,14,14,14,14,14,14,14,14,14,14,14,14,14,14,14,14,14,14,14,14,14,14,14,14,14,14,14,14,14,14,14   ],
   [
14,14,14,14,14,14,14,14,14,14,14,14,14,14,14,14,14,14,14,14,14,14,14,14,14,14,14,14,14,14,14,14   ],
   [
14,14,14,14,14,14,14,14,14,14,14,14,14,14,14,14,14,14,14,14,14,14,14,14,14,14,14,14,14,14,14,14   ],
   [
14,14,14,14,14,14,14,14,14,14,14,14,14,14,14,14,14,14,14,14,14,14,14,14,14,14,14,14,14,14,14,14   ],
   [
14,14,14,14,14,14,14,14,14,14,15,14,14,14,14,14,14,14,14,14,14,14,14,14,14,14,14,14,14,14,14,14   ],
   [
14,14,14,14,14,14,14,14,14,14,14,14,14,14,14,14,14,14,14,14,14,14,14,14,14,14,14,14,14,14,14,14   ],
   [
14,14,14,14,14,14,14,14,14,14,14,14,14,14,14,14,14,14,14,14,14,14,14,14,14,14,14,14,14,14,14,14   ],
   [
14,14,14,14,14,14,14,14,14,14,14,14,14,14,15,14,14,14,14,14,14,14,14,14,14,14,14,14,14,14,14,14   ],
   [
14,14,14,14,14,14,14,14,14,14,14,14,14,14,14,14,14,14,14,14,14,14,14,14,14,14,14,14,14,14,14,14   ],
   [
14,14,14,14,14,14,14,14,14,14,14,14,14,14,14,14,14,14,14,14,14,14,14,14,14,14,14,14,14,14,14,14   ],
   [
14,14,14,14,14,14,14,14,14,14,14,15,14,14,14,14,14,14,14,14,14,14,14,14,14,14,14,14,14,14,14,14   ],
   [
14,14,14,14,14,14,14,14,14,14,14,14,14,14,14,14,14,14,14,14,14,14,14,14,14,14,14,14,14,14,14,14   ],
   [
14,14,14,14,14,14,14,14,14,14,14,14,14,14,14,14,14,14,14,14,14,14,14,14,14,14,14,14,14,14,14,14   ],
   [
14,14,14,14,14,14,14,14,14,14,14,14,14,14,14,14,14,14,14,14,14,14,14,14,14,14,14,14,14,14,14,14   ],
   [
14,14,14,14,14,14,14,14,14,14,14,14,14,14,14,14,14,14,14,14,14,14,14,14,14,14,14,14,14,14,14,14   ],
   [
14,14,14,14,14,14,14,14,14,14,14,14,14,14,14,14,14,14,14,14,14,14,14,14,14,14,14,14,14,14,14,14   ],
   [
14,14,14,14,14,14,14,14,14,14,14,14,14,14,14,14,14,15,14,14,14,14,14,14,14,14,14,14,14,14,14,14   ],
   [
14,14,14,14,14,14,14,14,14,14,15,14,14,14,14,14,14,14,14,14,14,14,14,14,14,14,14,14,14,14,14,14   ],
   [
14,14,14,14,14,14,14,14,14,14,14,14,14,14,14,14,14,14,14,14,14,14,14,14,14,14,14,14,14,14,14,14   ],
   [
14,14,14,14,14,14,14,14,14,14,14,14,14,14,14,14,14,14,14,14,14,14,14,14,14,14,14,14,14,14,14,14   ],
   [
14,14,14,14,14,14,14,14,14,14,14,14,14,14,14,14,14,14,14,14,14,14,14,14,14,14,14,14,14,14,14,14   ],
   [
14,14,14,14,14,14,14,14,14,14,14,14,14,14,14,14,14,14,14,14,14,14,14,14,14,14,14,14,14,14,14,14   ],
   [
14,14,14,14,14,14,14,14,14,14,14,14,14,14,14,14,14,14,14,14,14,14,14,14,14,14,14,14,14,14,14,14   ],
   [
14,14,14,14,14,14,14,14,14,14,14,14,14,14,14,14,14,14,14,14,14,14,14,14,14,14,14,14,14,14,14,14   ],
   [
14,14,14,14,14,14,14,14,14,14,14,14,14,14,14,14,14,14,14,14,14,14,14,14,14,14,14,14,14,14,14,14   ],
   [
14,14,14,14,14,14,14,14,14,14,14,14,14,14,14,14,14,14,14,14,14,14,14,14,14,14,14,14,14,14,14,14   ]  ]
}
